[
  {
    "id": 1,
    "title": "EB-5 项目概述",
    "category": "基础知识",
    "subcategory": "项目基础",
    "description": "EB-5移民投资者计划允许符合条件的外国投资者通过投资于为美国工人创造就业机会的新商业企业来获得美国绿卡。",
    "shortDescription": "EB-5如何将投资与永久居留权联系起来。",
    "examples": [
      "在目标就业区（TEA）项目中投资80万美元",
      "创造或保留至少10个全职美国工作岗位"
    ],
    "dayNumber": 1,
    "isCompleted": false
  },
  {
    "id": 2,
    "title": "直接投资与区域中心投资",
    "category": "基础知识",
    "subcategory": "投资模式",
    "description": "投资者可以选择直接投资（自己管理业务运营）和区域中心投资（加入由专业人士管理的集合项目）。",
    "shortDescription": "比较两种主要的EB-5投资路径。",
    "examples": [
      "作为直接投资者拥有并经营一家餐厅",
      "通过区域中心参与房地产开发"
    ],
    "dayNumber": 2,
    "isCompleted": false
  },
  {
    "id": 3,
    "title": "就业创造要求",
    "category": "合规性",
    "subcategory": "美国公民及移民服务局标准",
    "description": "每项EB-5投资必须在投资者获得有条件居留权后的两年内，为合格的美国工人创造至少10个全职职位。",
    "shortDescription": "为什么就业创造是EB-5资格的核心。",
    "examples": [
      "为一个新开发项目招聘酒店员工",
      "计算区域中心项目支持的间接就业岗位"
    ],
    "dayNumber": 3,
    "isCompleted": false
  },
  {
    "id": 101,
    "title": "最低投资额",
    "category": "EB-5 基础",
    "subcategory": "资格要求",
    "description": "要获得EB-5项目资格，投资者必须在标准地区投资至少105万美元，或在目标就业区（TEA）或合格基础设施项目中投资80万美元。这些门槛于2022年设立，并可能每五年根据通货膨胀进行调整。",
    "shortDescription": "要获得EB-5项目资格，投资者必须在标准地区投资至少105万美元，或在目标就业区投资80万美元...",
    "examples": [
      "选择被归类为TEA的农村开发项目的投资者只需投资80万美元，而不是105万美元。",
      "位于非TEA城市区域的豪华房地产项目需要全额105万美元的投资才能获得EB-5资格。"
    ],
    "dayNumber": 1,
    "isCompleted": false
  },
  {
    "id": 102,
    "title": "就业创造要求",
    "category": "EB-5 基础",
    "subcategory": "资格要求",
    "description": "每项EB-5投资必须为美国工人创造至少10个全职工作岗位。这些职位必须维持至少两年，并且必须由合格的美国雇员填补，不包括投资者或其直系亲属。",
    "shortDescription": "每项EB-5投资必须为美国工人创造至少10个全职工作岗位。",
    "examples": [
      "一家新餐厅雇佣了12名全职员工来运营，满足了就业创造要求。",
      "区域中心项目可以使用IMPLAN等经济建模工具计算间接就业创造。"
    ],
    "dayNumber": 1,
    "isCompleted": false
  },
  {
    "id": 103,
    "title": "新商业企业",
    "category": "EB-5 基础",
    "subcategory": "资格要求",
    "description": "投资必须投向于1990年11月29日之后成立的新商业企业，或对现有业务进行重大重组或扩张的企业。被动投资，如购买个人使用的房地产，不符合资格。",
    "shortDescription": "投资必须投向于1990年11月29日之后成立的新商业企业，或进行重大重组或...",
    "examples": [
      "购买住宅物业不计为EB-5的合格投资。",
      "将本地连锁店的劳动力和实体规模扩大40%可以被视为EB-5下的重组业务。"
    ],
    "dayNumber": 1,
    "isCompleted": false
  },
  {
    "id": 104,
    "title": "资金的合法来源",
    "category": "EB-5 基础",
    "subcategory": "资格要求",
    "description": "投资者必须证明用于EB-5投资的资金是通过合法途径获得的。可接受的来源包括商业利润、薪水、贷款、赠与或继承。必须提供银行记录、纳税申报表和合同等文件来追溯资金的来源。",
    "shortDescription": "投资者必须证明用于EB-5投资的资金是通过合法途径获得的。",
    "examples": [
      "投资者出售了一家企业，并提供纳税申报表、销售协议和存款记录来显示投资资本的来源。",
      "如果资本是赠与，投资者必须提交赠与信以及捐赠者的财务文件以证明其合法来源。"
    ],
    "dayNumber": 1,
    "isCompleted": false
  },
  {
    "id": 105,
    "title": "资本处于风险中的要求",
    "category": "EB-5 基础",
    "subcategory": "资格要求",
    "description": "投资资本必须处于风险之中，以产生回报为目的。不能有任何回报或资金赎回的保证。投资必须面临损失的可能才能满足EB-5的规定。",
    "shortDescription": "投资资本必须处于风险之中，以产生回报为目的。",
    "examples": [
      "开发商不能保证投资将在五年后返还——这将使投资不合格。",
      "项目投资者明白，如果项目财务失败，他们可能无法收回资本。"
    ],
    "dayNumber": 1,
    "isCompleted": false
  },
  {
    "id": 106,
    "title": "全职工作定义",
    "category": "EB-5 基础",
    "subcategory": "资格要求",
    "description": "EB-5目的下的全职工作意味着每周至少工作35小时。它必须是永久性的，并由合格的美国工人填补——而不是临时、兼职或合同职位。",
    "shortDescription": "EB-5目的下的全职工作意味着每周至少工作35小时。",
    "examples": [
      "每周雇佣一名员工工作40小时符合全职工作的资格。",
      "两个兼职岗位加起来35小时不符合一个全职工作的资格。"
    ],
    "dayNumber": 1,
    "isCompleted": false
  },
  {
    "id": 107,
    "title": "目标就业区（TEA）资格",
    "category": "EB-5 基础",
    "subcategory": "资格要求",
    "description": "要获得80万美元的较低投资额资格，EB-5投资必须在TEA进行，TEA被定义为农村地区或高失业率地区（至少是全国平均水平的150%）。",
    "shortDescription": "要获得80万美元的较低投资额资格，EB-5投资必须在TEA进行，TEA被定义为农村地区或...",
    "examples": [
      "根据现行的美国公民及移民服务局规定，大都市区以外的农村小镇符合TEA的资格。",
      "如果全国失业率约为6%，那么一个城市区域失业率为9%的项目也符合资格。"
    ],
    "dayNumber": 1,
    "isCompleted": false
  },
  {
    "id": 108,
    "title": "投资者的积极角色",
    "category": "EB-5 基础",
    "subcategory": "资格要求",
    "description": "投资者必须参与新企业的管理。这一要求可以通过担任公司官员或董事会成员，或作为具有明确投票权的有限合伙人来满足。",
    "shortDescription": "投资者必须参与新企业的管理。",
    "examples": [
      "直接经营餐厅的投资者满足了积极管理的条件。",
      "作为区域中心的有限合伙人，投资者对重大决策拥有投票权——这也符合资格。"
    ],
    "dayNumber": 1,
    "isCompleted": false
  },
  {
    "id": 109,
    "title": "投资的持续性",
    "category": "EB-5 基础",
    "subcategory": "资格要求",
    "description": "EB-5投资必须在两年有条件居留期间保持“处于风险中”并被部署。提前返还资金可能导致I-829申请被拒。",
    "shortDescription": "EB-5投资必须在两年有条件居留期间保持“处于风险中”并被部署。",
    "examples": [
      "如果原始项目在I-829提交前结束，资金将被重新部署到另一个合格项目中。",
      "在两年期满前返还投资资本而未完成创造就业的要求可能导致被拒。"
    ],
    "dayNumber": 1,
    "isCompleted": false
  },
  {
    "id": 110,
    "title": "就业创造的证据",
    "category": "EB-5 基础",
    "subcategory": "资格要求",
    "description": "投资者必须提交文件以证明其投资导致了所需的就业创造。可接受的证据包括工资记录、税务文件和第三方经济分析。",
    "shortDescription": "投资者必须提交文件以证明其投资导致了所需的就业创造。",
    "examples": [
      "提交投资者企业雇佣的10名全职员工的W-2表格和工资分类账。",
      "区域中心提供一份经济学家的报告，模拟该项目带来的间接就业创造。"
    ],
    "dayNumber": 1,
    "isCompleted": false
  },
  {
    "id": 111,
    "title": "商业计划书要求",
    "category": "EB-5 基础",
    "subcategory": "资格要求",
    "description": "需要一份全面的商业计划书来证明新企业的可行性以及创造至少10个工作岗位的可能性。它必须包括财务预测、招聘时间表和详细的商业活动。",
    "shortDescription": "需要一份全面的商业计划书来证明新企业的可行性以及创造至少10个...",
    "examples": [
      "一家初创餐厅在其商业计划书中包括了5年财务预测和人员配置图。",
      "一家建筑公司提交了一份项目进度表，显示了招聘阶段和预期的就业创造日期。"
    ],
    "dayNumber": 1,
    "isCompleted": false
  },
  {
    "id": 112,
    "title": "投资证明",
    "category": "EB-5 基础",
    "subcategory": "资格要求",
    "description": "申请人必须提供明确的证据，证明投资资金已投入新的商业企业。这可以包括银行转账、认购协议和托管文件。",
    "shortDescription": "申请人必须提供明确的证据，证明投资资金已投入新的商业企业。",
    "examples": [
      "投资者提交了一份电汇收据和托管协议，以证明资金已妥善投入。",
      "一份签署的资本出资协议确认了投资者对企业的参与。"
    ],
    "dayNumber": 1,
    "isCompleted": false
  },
  {
    "id": 201,
    "title": "投资者及家人的永久居留权",
    "category": "EB-5 基础",
    "subcategory": "EB-5 的好处",
    "description": "EB-5项目为投资者、其配偶和21岁以下的未婚子女提供了一条直接获得美国永久居留权（绿卡）的途径。这使得整个家庭能够在美国任何地方生活、工作和学习。",
    "shortDescription": "EB-5项目为美国提供了一条直接的途径。",
    "examples": [
      "投资者及其配偶，以及两个十几岁的孩子，在EB-5申请成功批准后获得了绿卡。",
      "无论EB-5投资项目位于何处，该家庭都可以搬迁到美国任何一个州。"
    ],
    "dayNumber": 1,
    "isCompleted": false
  },
  {
    "id": 202,
    "title": "在美国任何地方生活和工作的自由",
    "category": "EB-5 基础",
    "subcategory": "EB-5 的好处",
    "description": "EB-5绿卡持有人不受特定雇主或地理区域的限制。他们可以在美国各地自由选择任何地点生活，并寻求就业、教育或商业机会。",
    "shortDescription": "EB-5绿卡持有人不受特定雇主或地理区域的限制。",
    "examples": [
      "一位投资者在德克萨斯州资助了一个项目，但选择与家人在加利福尼亚州定居。",
      "投资者的配偶可以在任何行业工作，甚至可以创办自己的企业。"
    ],
    "dayNumber": 1,
    "isCompleted": false
  },
  {
    "id": 203,
    "title": "通往美国公民身份的途径",
    "category": "EB-5 基础",
    "subcategory": "EB-5 的好处",
    "description": "在维持永久居留权五年（包括两年的有条件居留期）后，EB-5绿卡持有人可以申请美国公民身份，前提是他们满足所有入籍要求。",
    "shortDescription": "在维持永久居留权五年（包括两年的有条件居留期）后，EB-5绿卡持有人可以申请美国...",
    "examples": [
      "一位投资者于2025年获得绿卡，并有资格在2030年申请美国公民身份。",
      "EB-5申请中包含的子女在永久居留五年后也可以申请公民身份。",
      "18岁以上的子女可以独立入籍，而年幼的子女如果父母入籍，可能会自动获得公民身份。",
      "投资者的配偶在成为有条件居民五年后申请入籍。"
    ],
    "dayNumber": 1,
    "isCompleted": false
  },
  {
    "id": 204,
    "title": "无需担保",
    "category": "EB-5 基础",
    "subcategory": "EB-5 的好处",
    "description": "与基于就业或家庭的移民不同，EB-5项目不需要美国雇主或家庭成员为申请人提供担保。投资者根据其资本投资独立获得资格。",
    "shortDescription": "与基于就业或家庭的移民不同，EB-5项目不需要美国...",
    "examples": [
      "一位来自巴西的企业家投资了一个合格的项目，并在没有工作机会或家庭关系的情况下获得了绿卡。",
      "EB-5申请人不受同样漫长的基于担保的移民排期的限制。"
    ],
    "dayNumber": 1,
    "isCompleted": false
  },
  {
    "id": 205,
    "title": "子女的教育优势",
    "category": "EB-5 基础",
    "subcategory": "EB-5 的好处",
    "description": "EB-5投资者的子女有资格作为居民在美国学校就读，通常可以享受公立大学的州内学费。他们还避免了学生签证的限制，在学习期间有更多的就业灵活性。",
    "shortDescription": "EB-5投资者的子女有资格在美国就读。",
    "examples": [
      "一位EB-5投资者的孩子在加州一所大学就读，并支付了较低的州内学费。",
      "与F-1学生不同，EB-5持有人的子女可以申请实习或工作，而无需特殊许可。"
    ],
    "dayNumber": 1,
    "isCompleted": false
  },
  {
    "id": 206,
    "title": "创业能力",
    "category": "EB-5 基础",
    "subcategory": "EB-5 的好处",
    "description": "绿卡持有人可以自由地在美国建立或投资企业，而无需额外的工作授权。这对于希望管理或扩展其企业的企业家尤其有利。",
    "shortDescription": "绿卡持有人可以自由地在美国建立或投资企业。",
    "examples": [
      "一位投资者在纽约开设了一家新的咖啡连锁店，并雇佣了美国员工，无需任何进一步的移民步骤。",
      "投资者可以将其在国外的现有业务扩展到美国市场。"
    ],
    "dayNumber": 1,
    "isCompleted": false
  },
  {
    "id": 207,
    "title": "旅行灵活性",
    "category": "EB-5 基础",
    "subcategory": "EB-5 的好处",
    "description": "有了绿卡，EB-5投资者及其家人可以自由进出美国。他们不受通常适用于临时工作或学生签证持有人的签证限制。",
    "shortDescription": "有了绿卡，EB-5投资者及其家人可以自由进出美国。",
    "examples": [
      "一位EB-5投资者因商务而出国旅行，并无需签证即可重新进入美国。",
      "绿卡持有人可以利用其身份探望国外的家人，并自由返回美国。"
    ],
    "dayNumber": 1,
    "isCompleted": false
  },
  {
    "id": 208,
    "title": "退休机会",
    "category": "EB-5 基础",
    "subcategory": "EB-5 的好处",
    "description": "EB-5投资者可以利用其永久居民身份在美国退休，享受医疗保健、生活质量以及日后担保其他家庭成员的能力。",
    "shortDescription": "EB-5投资者可以利用其永久居民身份在美国退休，享受医疗保健、生活质量以及...",
    "examples": [
      "一位退休投资者在佛罗里达州定居，并在成为美国公民后可以完全享受医疗保险。",
      "永久居留权允许投资者通过基于家庭的移民将年迈的父母带到美国。"
    ],
    "dayNumber": 1,
    "isCompleted": false
  },
  {
    "id": 209,
    "title": "相对较快的绿卡途径",
    "category": "EB-5 基础",
    "subcategory": "EB-5 的好处",
    "description": "与许多其他移民项目相比，EB-5提供了一条相对较快的获得永久居留权的途径——特别是对于来自没有签证积压的国家或投资于预留签证类别（农村或高失业率地区）的申请人。",
    "shortDescription": "与许多其他移民项目相比，EB-5提供了一条相对较快的获得永久居留权的途径——特别是对于申请人...",
    "examples": [
      "一位来自低需求国家的投资者在提交申请后的18-24个月内获得了有条件绿卡。",
      "对农村TEA的投资可能有资格获得优先处理和预留签证配额。"
    ],
    "dayNumber": 1,
    "isCompleted": false
  },
  {
    "id": 210,
    "title": "投资机会",
    "category": "EB-5 基础",
    "subcategory": "EB-5 的好处",
    "description": "除了移民福利外，EB-5投资者还可能根据项目结构获得投资回报。虽然主要目标是绿卡，但一些项目也提供适度的回报或股权。",
    "shortDescription": "除了移民福利外，EB-5投资者还可能根据项目结构获得投资回报。",
    "examples": [
      "一个区域中心项目除了移民福利外，还向投资者提供1%的年回报率。",
      "一些直接投资者保留了成长中企业的股权，并长期获得利润。"
    ],
    "dayNumber": 1,
    "isCompleted": false
  },
  {
    "id": 211,
    "title": "与其他绿卡持有人相同的福利",
    "category": "EB-5 基础",
    "subcategory": "EB-5 的好处",
    "description": "一旦授予，EB-5绿卡提供与任何其他永久居民卡相同的权利。这包括合法工作授权、公共教育、驾照和获得某些医疗保健服务的权利。",
    "shortDescription": "一旦授予，EB-5绿卡提供与任何其他永久居民卡相同的权利。",
    "examples": [
      "EB-5投资者可以为他们的孩子申请社会安全号码、驾照和公立学校入学。",
      "在满足规定的居住期后，他们也有资格申请医疗保险。"
    ],
    "dayNumber": 1,
    "isCompleted": false
  },
  {
    "id": 212,
    "title": "家庭团聚",
    "category": "EB-5 基础",
    "subcategory": "EB-5 的好处",
    "description": "EB-5项目使家庭能够一起移民。主要申请人、其配偶和21岁以下的子女都在同一份申请下处理，有助于在移民过程中保持家庭团聚。",
    "shortDescription": "EB-5项目使家庭能够一起移民。",
    "examples": [
      "一个投资者的整个家庭根据一份EB-5申请搬到美国。",
      "孩子们可以立即上学并融入美国社会，而父母则经营企业。"
    ],
    "dayNumber": 1,
    "isCompleted": false
  },
  {
    "id": 301,
    "title": "EB-5 项目的创立 (1990)",
    "category": "EB-5 基础",
    "subcategory": "EB-5 的历史",
    "description": "EB-5 移民投资者项目由美国国会于 1990 年通过《移民法》创立。它旨在吸引外国投资进入美国经济，并通过为合格投资提供合法永久居留权来刺激就业增长。",
    "shortDescription": "EB-5 移民投资者项目由美国创立。",
    "examples": [
      "1990 年的法律规定了 100 万美元的投资门槛，以及农村或高失业率地区的 50 万美元门槛。",
      "最初，由于法规不明确和认知有限，该项目相对不为人知且未被充分利用。"
    ],
    "dayNumber": 1,
    "isCompleted": false
  },
  {
    "id": 302,
    "title": "区域中心的引入 (1992)",
    "category": "EB-5 基础",
    "subcategory": "EB-5 的历史",
    "description": "1992 年，国会启动了移民投资者试点项目，引入了 EB-5 区域中心。这些实体旨在促进集合投资，并允许通过经济建模进行间接就业创造。",
    "shortDescription": "1992 年，国会启动了移民投资者试点项目，引入了 EB-5 区域中心。",
    "examples": [
      "区域中心使投资者能够支持大型项目，如房地产开发，而无需管理日常运营。",
      "这项创新通过使被动投资者更容易参与，帮助推广了 EB-5。"
    ],
    "dayNumber": 1,
    "isCompleted": false
  },
  {
    "id": 303,
    "title": "早期采用率低",
    "category": "EB-5 基础",
    "subcategory": "EB-5 的历史",
    "description": "在整个 1990 年代，EB-5 项目的参与度仍然有限。由于缺乏推广、行政延误和令人困惑的规则，该项目举步维艰。在早期，每年签发的签证不到 1,000 个。",
    "shortDescription": "在整个 1990 年代，EB-5 项目的参与度仍然有限。",
    "examples": [
      "1995 年，仅授予了数百个 EB-5 签证，而签证上限为 10,000 个。",
      "由于法律不确定性和美国公民及移民服务局的指导不明确，许多潜在投资者避免了 EB-5。"
    ],
    "dayNumber": 1,
    "isCompleted": false
  },
  {
    "id": 304,
    "title": "2000 年代初的改革努力",
    "category": "EB-5 基础",
    "subcategory": "EB-5 的历史",
    "description": "在 2000 年代初，美国政府发布了澄清备忘录和先例，以提高 EB-5 项目的透明度和投资者信心。这包括像 Matter of Ho 和 Matter of Izummi 这样的关键决定，这些决定定义了商业计划和投资标准。",
    "shortDescription": "在 2000 年代初，美国...",
    "examples": [
      "Matter of Ho 先例确立了可信商业计划的要求。",
      "这些改革有助于防止欺诈性或含糊不清的投资获得批准。"
    ],
    "dayNumber": 1,
    "isCompleted": false
  },
  {
    "id": 305,
    "title": "2008 年金融危机期间的增长",
    "category": "EB-5 基础",
    "subcategory": "EB-5 的历史",
    "description": "2008 年的金融危机使得传统融资渠道变得稀缺，促使美国开发商转向 EB-5 投资者寻求资金。这标志着该项目受欢迎程度和增长的一个转折点。",
    "shortDescription": "2008 年的金融危机使得传统融资渠道变得稀缺，促使美国...",
    "examples": [
      "纽约、加利福尼亚和佛罗里达的房地产项目开始积极使用 EB-5 资金。",
      "2008 年至 2015 年间，EB-5 为美国项目筹集了超过 200 亿美元的外国投资。"
    ],
    "dayNumber": 1,
    "isCompleted": false
  },
  {
    "id": 306,
    "title": "中国申请人激增 (2010 年代)",
    "category": "EB-5 基础",
    "subcategory": "EB-5 的历史",
    "description": "在 2010 年代，大多数 EB-5 投资者是中国国民。由于每个国家的签证上限，需求激增，导致签证积压和漫长的等待时间。",
    "shortDescription": "在 2010 年代，大多数 EB-5 投资者是中国国民。",
    "examples": [
      "在其高峰期，中国占所有 EB-5 签证申请的 80% 以上。",
      "由于超额认购，中国申请人面临超过 5-10 年的等待时间。"
    ],
    "dayNumber": 1,
    "isCompleted": false
  },
  {
    "id": 307,
    "title": "杰伊峰欺诈丑闻 (2016)",
    "category": "EB-5 基础",
    "subcategory": "EB-5 的历史",
    "description": "2016 年，佛蒙特州杰伊峰滑雪胜地发生了一起重大的 EB-5 欺诈案件。项目开发商滥用投资者资金，导致美国证券交易委员会介入，并对该项目进行了重大改革。",
    "shortDescription": "2016 年，佛蒙特州杰伊峰滑雪胜地发生了一起重大的 EB-5 欺诈案件。",
    "examples": [
      "超过 2 亿美元被滥用，影响了数百名投资者。",
      "该事件凸显了 EB-5 项目需要加强监督和透明度。"
    ],
    "dayNumber": 1,
    "isCompleted": false
  },
  {
    "id": 308,
    "title": "现代化规则 (2019)",
    "category": "EB-5 基础",
    "subcategory": "EB-5 的历史",
    "description": "2019 年 11 月实施的 EB-5 现代化规则将 TEA 项目的最低投资额提高到 90 万美元，并改革了 TEA 的指定。它旨在减少滥用行为并增强项目完整性。",
    "shortDescription": "2019 年 11 月实施的 EB-5 现代化规则将 TEA 项目的最低投资额提高到 90 万美元，并改革了...",
    "examples": [
      "TEA 的最低投资额从 50 万美元增加到 90 万美元。",
      "TEA 指定权从各州转移到联邦政府（美国公民及移民服务局）。"
    ],
    "dayNumber": 1,
    "isCompleted": false
  },
  {
    "id": 309,
    "title": "法院撤销 2019 年规则 (2021)",
    "category": "EB-5 基础",
    "subcategory": "EB-5 的历史",
    "description": "2021 年 6 月，一家联邦法院因程序问题撤销了 2019 年的现代化规则。这暂时将投资门槛降回 50 万美元，并导致市场不确定性。",
    "shortDescription": "2021 年 6 月，一家联邦法院因程序问题撤销了 2019 年的现代化规则。",
    "examples": [
      "2021 年的几个月里，投资者争相在较低的 50 万美元门槛下提交申请。",
      "法院的裁决在投资者、开发商和律师中造成了混乱。"
    ],
    "dayNumber": 1,
    "isCompleted": false
  },
  {
    "id": 310,
    "title": "区域中心项目失效 (2021)",
    "category": "EB-5 基础",
    "subcategory": "EB-5 的历史",
    "description": "EB-5 区域中心项目于 2021 年 6 月到期，当时国会未能重新授权。该项目的中断延迟了处理，并给行业带来了重大干扰。",
    "shortDescription": "EB-5 区域中心项目于 2021 年 6 月到期，当时国会未能重新授权。",
    "examples": [
      "近一年来，没有接受通过区域中心提交的新 I-526 申请。",
      "正在进行的项目中的投资者陷入困境，等待立法行动。"
    ],
    "dayNumber": 1,
    "isCompleted": false
  },
  {
    "id": 311,
    "title": "EB-5 改革与诚信法案 (2022)",
    "category": "EB-5 基础",
    "subcategory": "EB-5 的历史",
    "description": "2022 年 3 月，国会通过了《EB-5 改革与诚信法案》，重新授权区域中心项目，并引入了严格的诚信和合规措施，包括为农村和贫困地区预留签证。",
    "shortDescription": "2022 年 3 月，国会通过了《EB-5 改革与诚信法案》，重新授权区域中心项目，并引入了严格的...",
    "examples": [
      "该法案将区域中心重新授权至 2027 年，并为 TEA 和基础设施项目预留了 32% 的签证。",
      "它还引入了强制性审计、背景调查和资金追踪系统。"
    ],
    "dayNumber": 1,
    "isCompleted": false
  },
  {
    "id": 312,
    "title": "签证预留和农村优先",
    "category": "EB-5 基础",
    "subcategory": "EB-5 的历史",
    "description": "2022 年改革法案设立了签证预留，以优先考虑对农村地区 (20%)、高失业率地区 (10%) 和基础设施项目 (2%) 的投资。这些类别受益于更快的处理速度和更少的积压。",
    "shortDescription": "2022 年改革法案设立了签证预留，以优先考虑对农村地区 (20%)、高失业率地区 (10%) 和...",
    "examples": [
      "由于预留类别的处理，农村项目的投资者可能会更快地获得签证。",
      "签证预留鼓励在大都市区以外的经济发展。"
    ],
    "dayNumber": 1,
    "isCompleted": false
  },
  {
    "id": 401,
    "title": "C5 签证类别",
    "category": "EB-5 基础",
    "subcategory": "EB-5 签证类型",
    "description": "C5 类别指的是在非 TEA（目标就业区）的商业企业进行直接投资的 EB-5 投资者。这是指定区域外直接投资者的标准分类。",
    "shortDescription": "C5 类别指的是在非 TEA（目标就业区）的商业企业进行直接投资的 EB-5 投资者...",
    "examples": [
      "一位投资者在美国一个主要城市向一家制造企业投资了 105 万美元，并获得了 C5 签证。",
      "当项目不位于农村或高失业率地区时，适用 C5。"
    ],
    "dayNumber": 1,
    "isCompleted": false
  },
  {
    "id": 402,
    "title": "T5 签证类别",
    "category": "EB-5 基础",
    "subcategory": "EB-5 签证类型",
    "description": "T5 类别适用于其投资位于目标就业区 (TEA) 的直接 EB-5 投资者。这允许将投资门槛降低到 80 万美元。",
    "shortDescription": "T5 类别适用于其投资位于目标就业区 (TEA) 的直接 EB-5 投资者。",
    "examples": [
      "在农村地区的直接投资符合 T5 资格，并且只需要 80 万美元。",
      "投资者在高失业率地区创办企业，并根据 T5 类别进行申请。"
    ],
    "dayNumber": 1,
    "isCompleted": false
  },
  {
    "id": 403,
    "title": "I5 和 R5 签证类别",
    "category": "EB-5 基础",
    "subcategory": "EB-5 签证类型",
    "description": "I5 和 R5 是为使用区域中心途径的投资者保留的。I5 用于非 TEA 地区的投资，而 R5 用于 TEA 地区的投资。这些类别允许通过区域中心项目进行间接就业创造。",
    "shortDescription": "I5 和 R5 是为使用区域中心途径的投资者保留的。",
    "examples": [
      "一位投资者通过农村地区的区域中心向酒店开发项目捐款，并获得了 R5 签证。",
      "当区域中心项目不位于 TEA 时，使用 I5。"
    ],
    "dayNumber": 1,
    "isCompleted": false
  },
  {
    "id": 404,
    "title": "预留签证类别 (2022 年后)",
    "category": "EB-5 基础",
    "subcategory": "EB-5 签证类型",
    "description": "根据 2022 年 EB-5 改革与诚信法案，每年有 32% 的 EB-5 签证被预留：20% 用于农村项目，10% 用于高失业率 TEA，2% 用于基础设施项目。这些项目有单独的排队和更快的处理速度。",
    "shortDescription": "根据 2022 年 EB-5 改革与诚信法案，每年有 32% 的 EB-5 签证被预留：20% 用于农村项目，10% 用于...",
    "examples": [
      "一个农村基础设施投资有资格获得两个不同的预留类别：农村和基础设施。",
      "预留签证类别的投资者可以跳过未预留签证的排队。"
    ],
    "dayNumber": 1,
    "isCompleted": false
  },
  {
    "id": 405,
    "title": "未预留签证类别",
    "category": "EB-5 基础",
    "subcategory": "EB-5 签证类型",
    "description": "未预留的 EB-5 签证是项目不属于农村、高失业率或基础设施类别的投资者的默认类别。这些签证约占年度总配额的 68%。",
    "shortDescription": "未预留的 EB-5 签证是项目不属于农村、高失业率或基础设施类别的投资者的默认类别...",
    "examples": [
      "一位在豪华城市酒店的 EB-5 投资者属于未预留签证类别。",
      "来自需求量大的国家的申请人可能会在此类别中遇到等待时间。"
    ],
    "dayNumber": 1,
    "isCompleted": false
  },
  {
    "id": 406,
    "title": "有条件永久居留权",
    "category": "EB-5 基础",
    "subcategory": "EB-5 签证类型",
    "description": "所有 EB-5 签证获得者最初都会获得为期两年的有条件永久居留权。在此期间，他们必须履行创造就业和维持投资的要求，才能获得 10 年期的绿卡。",
    "shortDescription": "所有 EB-5 签证获得者最初都会获得为期两年的有条件永久居留权。",
    "examples": [
      "获得 EB-5 签证后，投资者作为有条件居民进入美国。",
      "要取消条件，投资者必须在第二周年之前的 90 天内提交 I-829 表格。"
    ],
    "dayNumber": 1,
    "isCompleted": false
  },
  {
    "id": 407,
    "title": "签证公告和积压",
    "category": "EB-5 基础",
    "subcategory": "EB-5 签证类型",
    "description": "美国国务院每月发布的签证公告显示了哪些 EB-5 申请人有资格获得签证。由于每个国家的上限，一些国家可能会出现积压。",
    "shortDescription": "美国国务院每月发布的签证公告...",
    "examples": [
      "由于需求超过年度签证限额，来自印度和中国的申请人可能会面临等待时间。",
      "投资者应跟踪签证公告，以了解其优先日期何时生效。"
    ],
    "dayNumber": 1,
    "isCompleted": false
  },
  {
    "id": 408,
    "title": "EB-5 下的家庭成员",
    "category": "EB-5 基础",
    "subcategory": "EB-5 签证类型",
    "description": "EB-5 投资者的配偶和 21 岁以下的未婚子女可以作为衍生受益人获得有条件绿卡。他们获得与主要申请人相同的签证类型和福利。",
    "shortDescription": "EB-5 投资者的配偶和 21 岁以下的未婚子女可以作为衍生受益人获得有条件绿卡。",
    "examples": [
      "投资者的 19 岁子女和配偶与主要申请人一起获得有条件绿卡。",
      "衍生家庭成员也必须与主要申请人一起提交 I-829 以取消条件。"
    ],
    "dayNumber": 1,
    "isCompleted": false
  },
  {
    "id": 501,
    "title": "直接投资的定义",
    "category": "投资",
    "subcategory": "直接投资",
    "description": "EB-5项目中的直接投资意味着投资者亲自参与管理一个新的商业企业，而不使用区域中心。投资必须创造至少10个直接的全职工作岗位。",
    "shortDescription": "EB-5项目中的直接投资意味着投资者亲自参与管理一个新的商业企业，而不使用...",
    "examples": [
      "投资者开设一家餐厅并直接监督运营和员工。",
      "由投资者资助和运营的制造厂符合直接EB-5的资格。"
    ],
    "dayNumber": 1,
    "isCompleted": false
  },
  {
    "id": 502,
    "title": "创造的就业必须是直接的",
    "category": "投资",
    "subcategory": "直接投资",
    "description": "在直接EB-5投资中，所有创造的就业必须是直接的，并且可以在企业内部进行核实。间接或引致的就业不计入EB-5要求。",
    "shortDescription": "在直接EB-5投资中，所有创造的就业必须是直接的，并且可以在企业内部进行核实。",
    "examples": [
      "该企业雇佣了12名员工，并为每个人提供了工资记录和职位描述。",
      "在直接EB-5项目中，不允许使用第三方模型来创造就业。"
    ],
    "dayNumber": 1,
    "isCompleted": false
  },
  {
    "id": 503,
    "title": "需要积极的管理角色",
    "category": "投资",
    "subcategory": "直接投资",
    "description": "投资者必须积极参与企业的管理。这可以通过担任公司官员、董事或日常运营经理来履行。",
    "shortDescription": "投资者必须积极参与企业的管理。",
    "examples": [
      "投资者担任首席执行官的职位，并负责招聘和战略。",
      "在公司董事会中担任具有重要决策权的职务，也符合积极参与的资格。"
    ],
    "dayNumber": 1,
    "isCompleted": false
  },
  {
    "id": 504,
    "title": "常见的直接投资行业",
    "category": "投资",
    "subcategory": "直接投资",
    "description": "直接EB-5投资的热门行业包括餐饮、零售特许经营、制造业、物流和服务业。这些行业通常可以清楚地创造就业并允许直接参与。",
    "shortDescription": "直接EB-5投资的热门行业包括餐饮、零售特许经营、制造业、物流和服务业。",
    "examples": [
      "一位投资者开设了三家赛百味特许经营店，并雇佣了30多名员工。",
      "一位科技企业家创办了一家软件开发公司，并雇佣了当地的程序员。"
    ],
    "dayNumber": 1,
    "isCompleted": false
  },
  {
    "id": 505,
    "title": "商业计划和文件",
    "category": "投资",
    "subcategory": "直接投资",
    "description": "全面的商业计划对于直接EB-5至关重要。它必须详细说明商业模式、招聘时间表、财务预测和公司的管理结构。",
    "shortDescription": "全面的商业计划对于直接EB-5至关重要。",
    "examples": [
      "投资者提供了一份为期5年的商业计划，包括营销策略和人员预测。",
      "招聘时间表和职位描述被包括在内，以证明创造就业的计划。"
    ],
    "dayNumber": 1,
    "isCompleted": false
  },
  {
    "id": 506,
    "title": "不允许集合投资",
    "category": "投资",
    "subcategory": "直接投资",
    "description": "与区域中心投资不同，直接EB-5不允许将多个投资者的资金集合到一个单一的企业中，除非每个投资者都创造了他们自己的10个工作岗位并满足其他标准。",
    "shortDescription": "与区域中心投资不同，直接EB-5不允许将多个投资者的资金集合到一个单一的企业中，除非...",
    "examples": [
      "两名投资者不能将160万美元的投资分摊到一家企业中，除非创造了20个工作岗位。",
      "每个投资者都必须与一个特定的创造就业计划相关联。"
    ],
    "dayNumber": 1,
    "isCompleted": false
  },
  {
    "id": 507,
    "title": "适合创业型投资者",
    "category": "投资",
    "subcategory": "直接投资",
    "description": "直接投资非常适合那些希望亲身控制其业务、并且能够自己管理日常运营和遵守美国公民及移民服务局要求的企业家。",
    "shortDescription": "直接投资非常适合那些希望亲身控制其业务、并且能够自己管理日常运营的企业家...",
    "examples": [
      "一位企业主从国外搬迁，在美国根据EB-5开设了一家类似的公司。",
      "具有管理经验的投资者更喜欢直接投资来控制增长和运营。"
    ],
    "dayNumber": 1,
    "isCompleted": false
  },
  {
    "id": 508,
    "title": "风险与责任",
    "category": "投资",
    "subcategory": "直接投资",
    "description": "直接投资者承担全部的商业风险和运营责任。如果企业失败或未能创造就业，投资者可能会失去获得永久居留权的资格。",
    "shortDescription": "直接投资者承担全部的商业风险和运营责任。",
    "examples": [
      "如果一家直接投资企业在一年后关闭，美国公民及移民服务局可能会因未满足创造就业的要求而拒绝取消条件。",
      "未能满足工资要求可能会危及投资者的I-829申请。"
    ],
    "dayNumber": 1,
    "isCompleted": false
  },
  {
    "id": 601,
    "title": "区域中心的定义",
    "category": "投资",
    "subcategory": "区域中心",
    "description": "区域中心是美国公民及移民服务局指定的经济单位，负责赞助 EB-5 项目。它促进了集合投资，并允许通过经济模型计算直接和间接的就业创造。",
    "shortDescription": "区域中心是美国公民及移民服务局指定的经济单位，负责赞助 EB-5 项目。",
    "examples": [
      "佛罗里达州的一个区域中心赞助了一个房地产项目，并从 50 名 EB-5 投资者那里筹集了资金。",
      "美国公民及移民服务局批准的区域中心通常专注于建筑、基础设施或能源项目。"
    ],
    "dayNumber": 1,
    "isCompleted": false
  },
  {
    "id": 602,
    "title": "允许间接创造就业",
    "category": "投资",
    "subcategory": "区域中心",
    "description": "区域中心的一个主要优势是，它们允许将间接和引致的就业计入 EB-5 就业创造要求，这基于经济影响分析。",
    "shortDescription": "区域中心的一个主要优势是，它们允许将间接和引致的就业计入 EB-5 就业创造...",
    "examples": [
      "在支持该项目的供应商或服务提供商处创造的就业岗位计为间接就业。",
      "使用 IMPLAN 模型，一个区域中心显示，预计该开发项目将为每个投资者创造 10 个以上的工作岗位。"
    ],
    "dayNumber": 1,
    "isCompleted": false
  },
  {
    "id": 603,
    "title": "集合投资",
    "category": "投资",
    "subcategory": "区域中心",
    "description": "区域中心将多个 EB-5 投资者的投资汇集到一个大型项目中。每个投资者仍必须单独满足最低资本和就业创造要求。",
    "shortDescription": "区域中心将多个 EB-5 投资者的投资汇集到一个大型项目中。",
    "examples": [
      "一个 1 亿美元的酒店项目汇集了 100 名 EB-5 投资者的资金，每人出资 100 万美元。",
      "集合的资本资助了在各个行业具有可衡量就业影响的主要基础设施。"
    ],
    "dayNumber": 1,
    "isCompleted": false
  },
  {
    "id": 604,
    "title": "投资者角色是被动的",
    "category": "投资",
    "subcategory": "区域中心",
    "description": "区域中心项目的 EB-5 投资者通常扮演被动角色，通常是有限合伙人。他们不参与日常管理，但保留对重大决策的投票权。",
    "shortDescription": "区域中心项目的 EB-5 投资者通常扮演被动角色，通常是有限合伙人。",
    "examples": [
      "投资者在有限责任公司中担任有限合伙人职位，并审查季度财务报告。",
      "被动投资者允许专业人士处理业务运营和项目开发。"
    ],
    "dayNumber": 1,
    "isCompleted": false
  },
  {
    "id": 605,
    "title": "管理费",
    "category": "投资",
    "subcategory": "区域中心",
    "description": "区域中心通常在投资额之外收取管理费。这些费用从 5 万美元到 8 万美元不等，用于支付项目管理、合规和法律费用。",
    "shortDescription": "区域中心通常在投资额之外收取管理费。",
    "examples": [
      "一位 EB-5 投资者向区域中心支付了 80 万美元的资本和 7 万美元的管理费。",
      "管理费用于经济报告、移民法律支持和尽职调查。"
    ],
    "dayNumber": 1,
    "isCompleted": false
  },
  {
    "id": 606,
    "title": "年度合规与报告",
    "category": "投资",
    "subcategory": "区域中心",
    "description": "区域中心必须向美国公民及移民服务局提交年度报告以维持其指定。这些报告包括项目更新、就业创造分析和投资者进展。",
    "shortDescription": "区域中心必须向美国公民及移民服务局提交年度报告以维持其指定。",
    "examples": [
      "一个区域中心每年提交 I-956G 表格，报告就业创造指标和投资者数据。",
      "不报告可能导致美国公民及移民服务局的指定被终止。"
    ],
    "dayNumber": 1,
    "isCompleted": false
  },
  {
    "id": 607,
    "title": "美国公民及移民服务局的监督与审计",
    "category": "投资",
    "subcategory": "区域中心",
    "description": "美国公民及移民服务局有权审计区域中心，并因不合规或欺诈而撤销其指定。2022 年的改革法案大大加强了监督要求。",
    "shortDescription": "美国公民及移民服务局有权审计区域中心，并因不合规或欺诈而撤销其指定。",
    "examples": [
      "杰伊峰案件导致了更严格的法规和审计协议。",
      "随机现场访问和资金追踪现在是美国公民及移民服务局合规检查的一部分。"
    ],
    "dayNumber": 1,
    "isCompleted": false
  },
  {
    "id": 608,
    "title": "区域中心的受欢迎程度",
    "category": "投资",
    "subcategory": "区域中心",
    "description": "超过 90% 的 EB-5 申请人选择区域中心项目，因为其就业创造的灵活性和减少的个人管理义务。",
    "shortDescription": "超过 90% 的 EB-5 申请人选择区域中心项目，因为其就业创造的灵活性和减少的个人管理...",
    "examples": [
      "区域中心在寻求被动移民选择的投资者中尤其受欢迎。",
      "来自国外的投资者更喜欢不立即搬迁或亲身经营企业。"
    ],
    "dayNumber": 1,
    "isCompleted": false
  },
  {
    "id": 701,
    "title": "什么是目标就业区 (TEA)？",
    "category": "投资",
    "subcategory": "目标就业区",
    "description": "目标就业区 (TEA) 是指农村地区或高失业率地区，由美国公民及移民服务局定义。在 TEA 进行的投资有资格获得 80 万美元的 EB-5 最低投资额。",
    "shortDescription": "目标就业区 (TEA) 是指农村地区或高失业率地区，由美国公民及移民服务局定义。",
    "examples": [
      "一个居民少于 20,000 人的农村农业小镇符合 TEA 的资格。",
      "一个失业率比全国平均水平高 150% 的城市社区被指定为 TEA。"
    ],
    "dayNumber": 1,
    "isCompleted": false
  },
  {
    "id": 702,
    "title": "农村地区 TEA 资格",
    "category": "投资",
    "subcategory": "目标就业区",
    "description": "要符合农村地区的资格，该地区必须位于大都市统计区 (MSA) 之外，并且人口少于 20,000 人。该指定鼓励 EB-5 投资于服务不足的农村社区。",
    "shortDescription": "要符合农村地区的资格，该地区必须位于大都市统计区 (MSA) 之外，并且人口少于 20,000 人。",
    "examples": [
      "爱达荷州中部一个远离任何主要城市的小镇，根据 EB-5 指南被认为是农村地区。",
      "根据 2022 年改革法案，农村 TEA 的项目获得签证优先权。"
    ],
    "dayNumber": 1,
    "isCompleted": false
  },
  {
    "id": 703,
    "title": "高失业率 TEA 标准",
    "category": "投资",
    "subcategory": "目标就业区",
    "description": "高失业率 TEA 是指失业率至少为全国平均水平 150% 的城市或郊区。这些地区必须有数据支持，并符合美国公民及移民服务局的标准。",
    "shortDescription": "高失业率 TEA 是指失业率至少为全国平均水平 150% 的城市或郊区。",
    "examples": [
      "底特律一个失业率为全国平均水平 1.5 倍的地区有资格成为 TEA。",
      "美国公民及移民服务局使用人口普查区和劳工部统计数据来验证资格。"
    ],
    "dayNumber": 1,
    "isCompleted": false
  },
  {
    "id": 704,
    "title": "TEA 认证和文件",
    "category": "投资",
    "subcategory": "目标就业区",
    "description": "自 2022 年起，美国公民及移民服务局现在决定 TEA 的资格，不再将其委托给各个州。投资者或项目赞助商必须在提交申请时提供支持 TEA 资格的数据。",
    "shortDescription": "自 2022 年起，美国公民及移民服务局现在决定 TEA 的资格，不再将其委托给各个州。",
    "examples": [
      "投资者必须在 I-526E 申请中提交失业数据和人口普查地图。",
      "项目赞助商将经济学家的 TEA 分析作为商业计划的一部分。"
    ],
    "dayNumber": 1,
    "isCompleted": false
  },
  {
    "id": 705,
    "title": "TEA 和降低的投资额",
    "category": "投资",
    "subcategory": "目标就业区",
    "description": "TEA 的指定允许 EB-5 投资者投资 80 万美元，而不是标准的 105 万美元。这种财政激励鼓励在最需要经济发展的地区进行投资。",
    "shortDescription": "TEA 的指定允许 EB-5 投资者投资 80 万美元，而不是标准的 105 万美元。",
    "examples": [
      "通过选择投资于高失业率 TEA，投资者节省了 25 万美元。",
      "由于这一降低的资本要求，大多数 EB-5 投资都在 TEA 进行。"
    ],
    "dayNumber": 1,
    "isCompleted": false
  },
  {
    "id": 706,
    "title": "TEA 项目的签证预留",
    "category": "投资",
    "subcategory": "目标就业区",
    "description": "2022 年 EB-5 改革与诚信法案引入了签证预留：20% 用于农村 TEA，10% 用于高失业率 TEA。这些类别获得优先处理和单独的签证排队。",
    "shortDescription": "2022 年 EB-5 改革与诚信法案引入了签证预留：20% 用于农村 TEA，10% 用于高失业率 TEA。",
    "examples": [
      "由于有 20% 的专用预留，农村项目的投资者可能会更快地获得签证。",
      "TEA 投资帮助投资者避免与标准签证类别相关的漫长等待时间。"
    ],
    "dayNumber": 1,
    "isCompleted": false
  },
  {
    "id": 707,
    "title": "TEA 投资的经济影响",
    "category": "投资",
    "subcategory": "目标就业区",
    "description": "TEA 投资旨在刺激贫困或服务不足地区的就业创造和经济活动。这些项目通常包括经济适用房、医院和小型企业发展。",
    "shortDescription": "TEA 投资旨在刺激贫困或服务不足地区的就业创造和经济活动。",
    "examples": [
      "一个高失业率的 TEA 项目包括建造一个社区健康诊所，创造了 40 个工作岗位。",
      "农村 TEA 投资可以支持宽带或公用事业等基础设施升级。"
    ],
    "dayNumber": 1,
    "isCompleted": false
  },
  {
    "id": 801,
    "title": "“处于风险中”是什么意思？",
    "category": "投资",
    "subcategory": "风险投资",
    "description": "EB-5 投资资金必须“处于风险中”，以产生回报为目的。这意味着不能有任何回报或赎回的保证，并且投资者必须面临财务损失的可能性。",
    "shortDescription": "EB-5 投资资金必须“处于风险中”，以产生回报为目的。",
    "examples": [
      "开发商不能承诺无论项目结果如何都偿还投资者。",
      "EB-5 项目的投资者接受潜在损失或延迟回报的商业风险。"
    ],
    "dayNumber": 1,
    "isCompleted": false
  },
  {
    "id": 802,
    "title": "不允许签订赎回协议",
    "category": "投资",
    "subcategory": "风险投资",
    "description": "任何允许投资者要求偿还或要求企业回购投资的协议都违反了“处于风险中”的规则。资本必须始终受到市场力量和结果的影响。",
    "shortDescription": "任何允许投资者要求偿还或要求企业回购投资的协议都违反了“处于风险中”的...",
    "examples": [
      "禁止规定企业在五年后回购投资的回购条款。",
      "美国公民及移民服务局曾拒绝过将投资视为具有还款条款的贷款的申请。"
    ],
    "dayNumber": 1,
    "isCompleted": false
  },
  {
    "id": 803,
    "title": "无保证回报",
    "category": "投资",
    "subcategory": "风险投资",
    "description": "EB-5 投资不能提供固定的、有保证的或最低的回报。提供即使是低但有保证的回报也违反了 EB-5 资格规则，因为它破坏了风险因素。",
    "shortDescription": "EB-5 投资不能提供固定的、有保证的或最低的回报。",
    "examples": [
      "提供 2% 保证年回报率的协议不符合 EB-5 的规定。",
      "所有回报都必须基于项目绩效，并可能遭受损失。"
    ],
    "dayNumber": 1,
    "isCompleted": false
  },
  {
    "id": 804,
    "title": "允许的商业结构",
    "category": "投资",
    "subcategory": "风险投资",
    "description": "EB-5 投资可以采取股权（所有权）或贷款的形式，前提是贷款是无担保的、次级的且无保证的。股权投资通常用于直接 EB-5 项目。",
    "shortDescription": "EB-5 投资可以采取股权（所有权）或贷款的形式，前提是贷款是无担保的、次级的且无保证的。",
    "examples": [
      "区域中心可以将投资者资本作为次级贷款提供给项目开发商。",
      "股权投资授予投资者所有权和利润的一部分，但不是保证回报。"
    ],
    "dayNumber": 1,
    "isCompleted": false
  },
  {
    "id": 805,
    "title": "使用托管账户",
    "category": "投资",
    "subcategory": "风险投资",
    "description": "资金可以存放在托管账户中，并在投资者 I-526 或 I-526E 申请批准后释放给项目。这种结构在早期阶段保护了投资者，而不会违反“处于风险中”的规则。",
    "shortDescription": "资金可以存放在托管账户中，并在投资者 I-526 或 I-526E 申请批准后释放给项目。",
    "examples": [
      "投资者的资金仅在他们的 I-526 获得美国公民及移民服务局批准后才从托管账户中释放。",
      "托管协议由美国公民及移民服务局审查，以确保资金在释放后处于“风险中”。",
      "投资者资金存放在托管账户中，只有在美国公民及移民服务局批准申请后才会释放。",
      "托管协议规定了谁控制资金以及在什么条件下释放资金。"
    ],
    "dayNumber": 1,
    "isCompleted": false
  },
  {
    "id": 806,
    "title": "维持期要求",
    "category": "投资",
    "subcategory": "风险投资",
    "description": "投资资金必须在有条件居留之日起至少两年内保持“处于风险中”并部署在企业中。过早撤回资本可能导致 I-829 申请被拒。",
    "shortDescription": "投资资金必须在有条件居留之日起至少两年内保持“处于风险中”并部署在企业中。",
    "examples": [
      "在两年有条件期结束前撤回的资金可能会危及绿卡资格。",
      "如果原始项目提前结束，允许将资金重新部署到另一个项目中。"
    ],
    "dayNumber": 1,
    "isCompleted": false
  },
  {
    "id": 807,
    "title": "资本的重新部署",
    "category": "投资",
    "subcategory": "风险投资",
    "description": "如果原始项目在维持期结束前结束，资本必须重新部署到另一个符合 EB-5 要求的活动中。这确保了投资仍然处于风险中，并支持创造就业。",
    "shortDescription": "如果原始项目在维持期结束前结束，资本必须重新部署到另一个符合 EB-5 要求的活动中。",
    "examples": [
      "酒店项目完成后，剩余资金被投资于一个仓库开发项目。",
      "重新部署必须在商业上合理的时间内，并在同一个新的商业企业中进行。"
    ],
    "dayNumber": 1,
    "isCompleted": false
  },
  {
    "id": 901,
    "title": "标准投资额",
    "category": "投资",
    "subcategory": "投资额",
    "description": "截至2022年，EB-5项目的标准最低投资额为1,050,000美元。这适用于不位于指定的目标就业区（TEA）或基础设施项目中的项目。",
    "shortDescription": "截至2022年，EB-5项目的标准最低投资额为1,050,000美元。",
    "examples": [
      "一位在洛杉矶市中心创业的投资者出资1,050,000美元。",
      "非TEA商业项目必须满足这一更高的投资门槛。"
    ],
    "dayNumber": 1,
    "isCompleted": false
  },
  {
    "id": 902,
    "title": "为TEA和基础设施减少投资",
    "category": "投资",
    "subcategory": "投资额",
    "description": "对于位于农村地区、高失业率地区或由公共机构管理指定的公共基础设施项目，最低投资额降至80万美元。",
    "shortDescription": "对于位于农村地区、高失业率地区或由公共机构管理的指定...",
    "examples": [
      "一位投资者向一个农村太阳能设施投资80万美元。",
      "由公共机构赞助的交通枢纽项目以较低的门槛获得资格。"
    ],
    "dayNumber": 1,
    "isCompleted": false
  },
  {
    "id": 903,
    "title": "每5年进行通货膨胀调整",
    "category": "投资",
    "subcategory": "投资额",
    "description": "根据2022年的EB-5改革与诚信法案，投资门槛将每五年根据通货膨胀进行调整，以反映经济状况并保持该计划的价值。",
    "shortDescription": "根据2022年的EB-5改革与诚信法案，投资门槛将每五年根据通货膨胀进行调整，以反映...",
    "examples": [
      "如果通货膨胀显著增加，80万美元的TEA门槛可能会在下一次更新中提高。",
      "下一次审查预计将在2027年进行，即2022年调整后的五年。"
    ],
    "dayNumber": 1,
    "isCompleted": false
  },
  {
    "id": 904,
    "title": "资本出资要求",
    "category": "投资",
    "subcategory": "投资额",
    "description": "EB-5投资资金必须不可撤销地投入企业，并且不得包括以EB-5企业资产为担保的借款。赠与或个人贷款在提供适当文件的情况下可能符合资格。",
    "shortDescription": "EB-5投资资金必须不可撤销地投入企业，并且不得包括以EB-5企业的资产为担保的借款...",
    "examples": [
      "一位投资者使用出售房产的收益作为他们的EB-5投资。",
      "如果亲属赠与的款项包括正式的赠与信和来源文件，则允许使用。"
    ],
    "dayNumber": 1,
    "isCompleted": false
  },
  {
    "id": 905,
    "title": "同一项目中的多个投资者",
    "category": "投资",
    "subcategory": "投资额",
    "description": "如果一个项目包括多个EB-5投资者，每个投资者都必须独立满足全部最低投资要求，并被记为创造了10个新的工作岗位。",
    "shortDescription": "如果一个项目包括多个EB-5投资者，每个投资者都必须独立满足全部最低投资要求，并被记为...",
    "examples": [
      "同一企业中的两名投资者每人投资80万美元，并分别与10个工作岗位相关联。",
      "每个投资者的资金必须是可追溯的，并在创造就业方面单独核算。"
    ],
    "dayNumber": 1,
    "isCompleted": false
  },
  {
    "id": 906,
    "title": "资金来源合规",
    "category": "投资",
    "subcategory": "投资额",
    "description": "无论投资金额多少，所有用于EB-5申请的资本都必须是合法来源。美国公民及移民服务局要求提供完整的追溯资金来源和合法路径的文件。",
    "shortDescription": "无论投资金额多少，所有用于EB-5申请的资本都必须是合法来源。",
    "examples": [
      "提交银行记录和纳税申报表，以显示投资者如何积累了80万美元。",
      "即使金额正确，未能证明合法来源也可能导致申请被拒。"
    ],
    "dayNumber": 1,
    "isCompleted": false
  },
  {
    "id": 1001,
    "title": "房地产开发项目",
    "category": "投资",
    "subcategory": "投资项目类型",
    "description": "房地产开发是EB-5投资类型中最常见的之一，特别是通过区域中心。项目通常包括酒店、多功能建筑或多户住宅。",
    "shortDescription": "房地产开发是EB-5投资类型中最常见的之一，特别是通过区域中心。",
    "examples": [
      "一位EB-5投资者参与一个区域中心项目，建造一家新的希尔顿酒店。",
      "高增长地区的多户公寓开发项目通常有资格获得EB-5资金。"
    ],
    "dayNumber": 1,
    "isCompleted": false
  },
  {
    "id": 1002,
    "title": "基础设施项目",
    "category": "投资",
    "subcategory": "投资项目类型",
    "description": "由政府机构或公私合作伙伴关系管理的基础设施项目可能有资格以较低的投资水平获得EB-5资格。这些项目包括交通、公用事业或水系统。",
    "shortDescription": "由政府机构或公私合作伙伴关系管理的基础设施项目可能有资格以较低的投资水平获得EB-5资格...",
    "examples": [
      "EB-5资本用于支持一个市政机场的扩建。",
      "一个公共机构与私人开发商合作，利用EB-5投资升级水管。"
    ],
    "dayNumber": 1,
    "isCompleted": false
  },
  {
    "id": 1003,
    "title": "制造业和工业项目",
    "category": "投资",
    "subcategory": "投资项目类型",
    "description": "直接EB-5投资者可以选择创办或扩建工厂、生产设施或其他工业企业。这些项目通常能产生大量的直接就业岗位。",
    "shortDescription": "直接EB-5投资者可以选择创办或扩建工厂、生产设施或其他工业企业。",
    "examples": [
      "一位投资者开设了一家家具制造厂，雇佣了20名工人。",
      "一家食品加工公司利用EB-5资金扩大生产。"
    ],
    "dayNumber": 1,
    "isCompleted": false
  },
  {
    "id": 1004,
    "title": "特许经营和零售业务",
    "category": "投资",
    "subcategory": "投资项目类型",
    "description": "EB-5投资者可以开设和经营特许经营企业，如餐馆或零售店。如果这些企业创造了至少10个全职工作岗位，它们就可以获得资格。",
    "shortDescription": "EB-5投资者可以开设和经营特许经营企业，如餐馆或零售店。",
    "examples": [
      "一位投资者开设了三家Dunkin'特许经营店，共有30名员工。",
      "对一家连锁超市的直接投资符合EB-5的资格。"
    ],
    "dayNumber": 1,
    "isCompleted": false
  },
  {
    "id": 1005,
    "title": "医疗保健和医疗设施",
    "category": "投资",
    "subcategory": "投资项目类型",
    "description": "与医疗保健相关的EB-5项目包括医院、养老中心或医疗诊所。这些项目通常通过区域中心开发，并能产生长期就业。",
    "shortDescription": "与医疗保健相关的EB-5项目包括医院、养老中心或医疗诊所。",
    "examples": [
      "一个由EB-5资助的养老院为护士和支持人员创造了60多个工作岗位。",
      "一个区域中心利用投资者资本开发了一个门诊医疗设施。"
    ],
    "dayNumber": 1,
    "isCompleted": false
  },
  {
    "id": 1006,
    "title": "技术和创新初创企业",
    "category": "投资",
    "subcategory": "投资项目类型",
    "description": "具有创业经验的EB-5投资者可以在软件、电子商务或医疗设备等领域创建科技公司。这些项目通常需要直接的EB-5途径。",
    "shortDescription": "具有创业经验的EB-5投资者可以在软件、电子商务或医疗设备等领域创建科技公司。",
    "examples": [
      "一位生物技术企业家创办了一家诊断实验室，并雇佣了15名专家。",
      "一家移动应用开发公司根据EB-5雇佣了12名软件工程师。"
    ],
    "dayNumber": 1,
    "isCompleted": false
  },
  {
    "id": 1007,
    "title": "教育和培训设施",
    "category": "投资",
    "subcategory": "投资项目类型",
    "description": "投资于特许学校、培训中心或大学附属设施，如果能产生合格的工作岗位并满足所有项目标准，则可能有资格获得EB-5。",
    "shortDescription": "投资于特许学校、培训中心或大学附属设施，如果能产生合格的工作岗位...",
    "examples": [
      "一所特许学校利用EB-5资金开发，并雇佣了教师和员工。",
      "一位投资者根据TEA指定，在农村地区资助了一个职业培训中心。"
    ],
    "dayNumber": 1,
    "isCompleted": false
  },
  {
    "id": 1008,
    "title": "酒店和娱乐",
    "category": "投资",
    "subcategory": "投资项目类型",
    "description": "娱乐综合体、活动中心和以旅游为导向的项目（如度假村）在明确记录了创造就业的情况下，是合格的EB-5投资。",
    "shortDescription": "娱乐综合体、活动中心和以旅游为导向的项目（如度假村）在明确记录了创造就业的情况下，是合格的EB-5投资...",
    "examples": [
      "一个国家公园扩建项目中的度假村由EB-5资本资助。",
      "一个多功能娱乐区创造了数百个工作岗位，并符合EB-5的资格。"
    ],
    "dayNumber": 1,
    "isCompleted": false
  },
  {
    "id": 1101,
    "title": "合法的个人储蓄",
    "category": "投资",
    "subcategory": "资金来源",
    "description": "EB-5投资者可以使用通过合法收入（如薪水、奖金、股息或自雇）积累的个人储蓄。需要提供完整的收入历史文件。",
    "shortDescription": "EB-5投资者可以使用通过合法收入（如薪水、奖金、股息或自雇）积累的个人储蓄。",
    "examples": [
      "一位投资者使用在一家跨国公司工作10年的薪水储蓄。",
      "工资单、雇佣合同和纳税申报表作为证据提交。"
    ],
    "dayNumber": 1,
    "isCompleted": false
  },
  {
    "id": 1102,
    "title": "出售财产所得",
    "category": "投资",
    "subcategory": "资金来源",
    "description": "投资者可以使用出售房地产或其他个人资产获得的资本。文件必须证明所有权、销售交易和收益转移。",
    "shortDescription": "投资者可以使用出售房地产或其他个人资产获得的资本。",
    "examples": [
      "在迪拜出售的一套公寓为EB-5投资带来了100万美元。",
      "投资者提交了地契、销售合同和银行转账记录。"
    ],
    "dayNumber": 1,
    "isCompleted": false
  },
  {
    "id": 1103,
    "title": "家庭成员的赠与",
    "category": "投资",
    "subcategory": "资金来源",
    "description": "EB-5资金可以作为亲属的赠与获得。必须包括一份经公证的赠与信，并且赠与人必须证明其资金的合法来源。",
    "shortDescription": "EB-5资金可以作为亲属的赠与获得。",
    "examples": [
      "一位父母向他们的孩子赠与80万美元用于EB-5投资。",
      "父母提供财务记录以显示赠与资金的来源。"
    ],
    "dayNumber": 1,
    "isCompleted": false
  },
  {
    "id": 1104,
    "title": "继承",
    "category": "投资",
    "subcategory": "资金来源",
    "description": "继承的钱或财产可以用于EB-5，只要文件显示了合法转移和死者财富的合法来源。",
    "shortDescription": "继承的钱或财产可以用于EB-5，只要文件显示了合法转移和死者财富的合法来源...",
    "examples": [
      "一位投资者继承了土地并将其出售以资助他们的EB-5申请。",
      "遗嘱、遗嘱认证和销售记录被用来追溯资金。"
    ],
    "dayNumber": 1,
    "isCompleted": false
  },
  {
    "id": 1105,
    "title": "商业利润",
    "category": "投资",
    "subcategory": "资金来源",
    "description": "投资者合法拥有的企业的利润可以用于EB-5。必须提供所有权、收入产生和财务记录。",
    "shortDescription": "投资者合法拥有的企业的利润可以用于EB-5。",
    "examples": [
      "一位投资者从一家物流公司提取股息来资助EB-5。",
      "提交了公司税务申报、银行对账单和注册文件。"
    ],
    "dayNumber": 1,
    "isCompleted": false
  },
  {
    "id": 1106,
    "title": "无担保个人贷款",
    "category": "投资",
    "subcategory": "资金来源",
    "description": "美国公民及移民服务局允许在EB-5中使用无担保个人贷款，前提是投资者个人承担责任，并且贷款不由EB-5企业资产担保。",
    "shortDescription": "美国公民及移民服务局允许在EB-5中使用无担保个人贷款，前提是投资者个人承担责任，并且贷款不由EB-5企业资产担保...",
    "examples": [
      "一位投资者以其个人信用向银行贷款并投资了这笔资金。",
      "贷款合同和责任证明与申请一起提交。"
    ],
    "dayNumber": 1,
    "isCompleted": false
  },
  {
    "id": 1107,
    "title": "有担保贷款（有条件）",
    "category": "投资",
    "subcategory": "资金来源",
    "description": "以投资者个人资产（而非EB-5企业资产）为担保的贷款可能被允许。必须包括适当的估价和留置权文件。",
    "shortDescription": "以投资者个人资产（而非EB-5企业资产）为担保的贷款可能被允许。",
    "examples": [
      "以投资者私人住宅为担保的贷款用于EB-5。",
      "评估和抵押文件提交给美国公民及移民服务局。"
    ],
    "dayNumber": 1,
    "isCompleted": false
  },
  {
    "id": 1108,
    "title": "多种资金来源",
    "category": "投资",
    "subcategory": "资金来源",
    "description": "投资者可以结合各种合法资金来源来达到EB-5投资门槛。每个来源都必须有明确的文件记录并且是合法获得的。",
    "shortDescription": "投资者可以结合各种合法资金来源来达到EB-5投资门槛。",
    "examples": [
      "一位投资者使用了储蓄、继承和家庭赠与的组合。",
      "每个部分都单独记录并包含在I-526申请中。"
    ],
    "dayNumber": 1,
    "isCompleted": false
  },
  {
    "id": 1201,
    "title": "项目业绩记录",
    "category": "房地产与商业",
    "subcategory": "选择房地产项目",
    "description": "审查开发商和区域中心过去的项目历史，包括成功的 EB-5 完成、创造就业和向投资者返还资本。这有助于降低投资风险。",
    "shortDescription": "审查开发商和区域中心过去的项目历史，包括成功的 EB-5 完成、创造就业和向投资者返还...",
    "examples": [
      "一个有完成五个 EB-5 项目并返还资本历史的开发商被认为是较低风险的。",
      "避免由首次开发商或有未解决的过去失败的开发商领导的项目。"
    ],
    "dayNumber": 1,
    "isCompleted": false
  },
  {
    "id": 1202,
    "title": "项目地点和需求",
    "category": "房地产与商业",
    "subcategory": "选择房地产项目",
    "description": "评估项目所在地区的需求和人口统计数据。位于经济驱动力强的增长地区的房产往往更成功。",
    "shortDescription": "评估项目所在地区的需求和人口统计数据。",
    "examples": [
      "德克萨斯州奥斯汀的一个多户住宅项目可能会受益于人口增长和住房需求。",
      "位于旅游业衰退地区的酒店存在较高的空置率和财务风险。"
    ],
    "dayNumber": 1,
    "isCompleted": false
  },
  {
    "id": 1203,
    "title": "TEA 资格",
    "category": "房地产与商业",
    "subcategory": "选择房地产项目",
    "description": "目标就业区 (TEA) 的项目有资格获得较低的投资门槛，并可能提供签证预留优势，特别是在农村或高失业率地区。",
    "shortDescription": "目标就业区 (TEA) 的项目有资格获得较低的投资门槛，并可能提供签证预留优势，特别是在...",
    "examples": [
      "位于农村 TEA 的项目可能允许投资者以 80 万美元的水平获得资格。",
      "TEA 身份可以提供优先签证处理和更短的等待时间。"
    ],
    "dayNumber": 1,
    "isCompleted": false
  },
  {
    "id": 1204,
    "title": "资本结构透明度",
    "category": "房地产与商业",
    "subcategory": "选择房地产项目",
    "description": "评估 EB-5 投资如何融入项目的整体资本结构。具有健康的债务股本比率和清晰的财务规划的项目可以降低风险。",
    "shortDescription": "评估 EB-5 投资如何融入项目的整体资本结构。",
    "examples": [
      "一个拥有 25% 开发商股权、50% 银行贷款和 25% EB-5 资金的项目可能被认为是平衡的。",
      "如果 EB-5 资金被用作唯一或主要来源，风险可能会升高。"
    ],
    "dayNumber": 1,
    "isCompleted": false
  },
  {
    "id": 1205,
    "title": "EB-5 投资者的退出策略",
    "category": "房地产与商业",
    "subcategory": "选择房地产项目",
    "description": "寻找一个明确定义且现实的退出策略，该策略概述了投资者在维持期后何时以及如何返还其资本。",
    "shortDescription": "寻找一个明确定义且现实的退出策略，该策略概述了投资者在维持期后何时以及如何返还其资本...",
    "examples": [
      "与 5-7 年后出售或再融资房产相关的退出策略是常见的。",
      "警惕含糊的承诺或缺乏关于投资者还款时间表的细节。"
    ],
    "dayNumber": 1,
    "isCompleted": false
  },
  {
    "id": 1206,
    "title": "创造就业预测",
    "category": "房地产与商业",
    "subcategory": "选择房地产项目",
    "description": "审查项目计划如何创造就业。寻找具有强大就业创造缓冲区的项目——每位投资者超过 10 个工作岗位——以最大限度地降低达不到标准的风险。",
    "shortDescription": "审查项目计划如何创造就业。",
    "examples": [
      "一个酒店项目预计每位投资者创造 15 个工作岗位，这比预计恰好 10 个工作岗位的项目提供了更多的保护。",
      "仅依赖间接就业创造的项目可能风险更大。"
    ],
    "dayNumber": 1,
    "isCompleted": false
  },
  {
    "id": 1207,
    "title": "第三方尽职调查",
    "category": "房地产与商业",
    "subcategory": "选择房地产项目",
    "description": "由法律、财务或移民专家进行的独立尽职调查报告可以提供有关项目可信度和结构的见解。",
    "shortDescription": "由法律、财务或移民专家进行的独立尽职调查报告可以提供有关项目可信度和结构的见解...",
    "examples": [
      "投资者要求第三方就项目是否符合 EB-5 规则出具法律意见。",
      "一家信誉良好的公司的经济报告评估了创造就业的假设。"
    ],
    "dayNumber": 1,
    "isCompleted": false
  },
  {
    "id": 1208,
    "title": "托管和资金流结构",
    "category": "房地产与商业",
    "subcategory": "选择房地产项目",
    "description": "了解投资者资金如何持有和释放。强大的项目使用第三方托管来持有资本，直到 I-526 批准并保持透明度。",
    "shortDescription": "了解投资者资金如何持有和释放。",
    "examples": [
      "投资者资金仅在美国公民及移民服务局批准其申请后才从托管账户中释放。",
      "一些项目立即释放资金，如果 I-526 被拒，这可能会增加风险。"
    ],
    "dayNumber": 1,
    "isCompleted": false
  },
  {
    "id": 1301,
    "title": "商业地产",
    "category": "房地产与商业",
    "subcategory": "房地产投资类型",
    "description": "商业地产项目包括写字楼、购物中心、工业园区和酒店。由于创造就业潜力大、资本需求量大，这些项目是常见的 EB-5 投资。",
    "shortDescription": "商业地产项目包括写字楼、购物中心、工业园区和酒店。",
    "examples": [
      "一位 EB-5 投资者资助建造一座出租给科技公司的 20 层写字楼。",
      "一个多功能商业建筑包括零售空间和商务中心。"
    ],
    "dayNumber": 1,
    "isCompleted": false
  },
  {
    "id": 1302,
    "title": "住宅房地产",
    "category": "房地产与商业",
    "subcategory": "房地产投资类型",
    "description": "住宅项目包括公寓楼、共管公寓和住宅开发。这些开发项目可能提供更快的建设时间和更稳定的入住率。",
    "shortDescription": "住宅项目包括公寓楼、共管公寓和住宅开发。",
    "examples": [
      "一个区域中心在一个不断发展的郊区开发了一座 200 套公寓的建筑。",
      "郊区住宅开发是为了满足当地家庭的住房需求而建造的。"
    ],
    "dayNumber": 1,
    "isCompleted": false
  },
  {
    "id": 1303,
    "title": "多功能开发项目",
    "category": "房地产与商业",
    "subcategory": "房地产投资类型",
    "description": "多功能项目将住宅、商业，有时还包括酒店或娱乐部分结合在一个开发项目中，从而增加了创造就业的多样性和租户吸引力。",
    "shortDescription": "多功能项目将住宅、商业，有时还包括酒店或娱乐部分结合在一个开发项目中，从而增加了...",
    "examples": [
      "一个市中心项目结合了酒店、零售商场和住宅单元。",
      "投资者从多种收入来源和就业来源中受益。"
    ],
    "dayNumber": 1,
    "isCompleted": false
  },
  {
    "id": 1304,
    "title": "酒店项目",
    "category": "房地产与商业",
    "subcategory": "房地产投资类型",
    "description": "酒店、度假村和会议中心由于在建设和持续运营（如人员配备、餐饮和管理）期间创造了大量就业机会，因此常用于 EB-5。",
    "shortDescription": "酒店、度假村和会议中心由于在建设和持续运营期间创造了大量就业机会，因此常用于 EB-5...",
    "examples": [
      "EB-5 投资者帮助资助了一个靠近会议中心的 300 间客房的酒店。",
      "豪华度假村开发项目包括高尔夫球场和水疗中心，创造了多样化的就业机会。"
    ],
    "dayNumber": 1,
    "isCompleted": false
  },
  {
    "id": 1305,
    "title": "学生和老年人住房",
    "category": "房地产与商业",
    "subcategory": "房地产投资类型",
    "description": "像宿舍或养老院这样的专门住房是不断增长的 EB-5 资产类别。这些开发项目提供可靠的租户和持续的基于员工的就业创造。",
    "shortDescription": "像宿舍或养老院这样的专门住房是不断增长的 EB-5 资产类别。",
    "examples": [
      "一个 EB-5 投资项目建造了配有医疗和护理人员的辅助生活公寓。",
      "大学附近的学生住房项目需求量大，通常完全出租。"
    ],
    "dayNumber": 1,
    "isCompleted": false
  },
  {
    "id": 1306,
    "title": "工业房地产",
    "category": "房地产与商业",
    "subcategory": "房地产投资类型",
    "description": "工业 EB-5 项目包括仓库、配送中心和物流枢纽。由于电子商务需求的增长和运营就业的创造，这些项目可能具有吸引力。",
    "shortDescription": "工业 EB-5 项目包括仓库、配送中心和物流枢纽。",
    "examples": [
      "一个 EB-5 仓库开发项目支持一个区域性运输网络。",
      "一个冷藏物流中心雇佣了技术人员、司机和支持人员。"
    ],
    "dayNumber": 1,
    "isCompleted": false
  },
  {
    "id": 1307,
    "title": "经济适用房项目",
    "category": "房地产与商业",
    "subcategory": "房地产投资类型",
    "description": "经济适用房项目满足社区需求，并经常获得地方支持或激励。它们与 EB-5 的目标一致，即在服务不足的地区创造就业和发展。",
    "shortDescription": "经济适用房项目满足社区需求，并经常获得地方支持或激励。",
    "examples": [
      "一位投资者帮助资助了一个城市 TEA 中的低收入租赁住房。",
      "这些项目通常有资格获得额外的税收抵免或公共拨款。"
    ],
    "dayNumber": 1,
    "isCompleted": false
  },
  {
    "id": 1401,
    "title": "市场需求的重要性",
    "category": "房地产与商业",
    "subcategory": "市场分析",
    "description": "评估市场需求对于确保项目成功和创造就业至关重要。强劲的需求可以降低空置风险，提高盈利能力，从而增加 EB-5 成功的可能性。",
    "shortDescription": "评估市场需求对于确保项目成功和创造就业至关重要。",
    "examples": [
      "一个靠近不断发展的大学的住宅开发项目入住率很高。",
      "市场分析显示，一个农村小镇对医疗服务的需求尚未得到满足。"
    ],
    "dayNumber": 1,
    "isCompleted": false
  },
  {
    "id": 1402,
    "title": "经济和人口趋势",
    "category": "房地产与商业",
    "subcategory": "市场分析",
    "description": "投资者应审查目标地区的人口增长、就业率和收入水平。这些指标反映了项目的长期可行性和可持续性。",
    "shortDescription": "投资者应审查目标地区的人口增长、就业率和收入水平。",
    "examples": [
      "一个物流项目得到了区域电子商务领域就业增长的支持。",
      "高 median 收入和低失业率支持了一项豪华公寓投资。"
    ],
    "dayNumber": 1,
    "isCompleted": false
  },
  {
    "id": 1403,
    "title": "竞争格局",
    "category": "房地产与商业",
    "subcategory": "市场分析",
    "description": "分析现有供应和竞争对手有助于评估该项目是填补了市场空白还是面临过度饱和，后者可能会阻碍收入和创造就业。",
    "shortDescription": "分析现有供应和竞争对手有助于评估该项目是填补了市场空白还是面临过度饱和，后者可能会...",
    "examples": [
      "一项可行性研究表明，一所州立大学附近的学生住房短缺。",
      "一个写字楼项目在商业空置率不断上升的市场中可能会举步维艰。"
    ],
    "dayNumber": 1,
    "isCompleted": false
  },
  {
    "id": 1404,
    "title": "第三方市场研究",
    "category": "房地产与商业",
    "subcategory": "市场分析",
    "description": "独立的市场研究提供了宝贵的见解，并提高了与美国公民及移民服务局和贷款机构的可信度。这些报告评估了创造就业的潜力和项目与区域需求的契合度。",
    "shortDescription": "独立的市场研究提供了宝贵的见解，并提高了与美国公民及移民服务局和贷款机构的可信度。",
    "examples": [
      "一家经济研究公司为一家零售综合体提供了一份市场需求研究报告。",
      "贷款机构和投资者依赖第三方报告来验证假设。"
    ],
    "dayNumber": 1,
    "isCompleted": false
  },
  {
    "id": 1405,
    "title": "地方政府和规划支持",
    "category": "房地产与商业",
    "subcategory": "市场分析",
    "description": "获得市政府或州发展计划的认可或被纳入其中可以验证需求，并增加项目成功的机会。支持性的分区和基础设施是关键信号。",
    "shortDescription": "获得市政府或州发展计划的认可或被纳入其中可以验证需求，并增加项目成功的机会。",
    "examples": [
      "一个被列入城市重建计划的项目获得了快速审批。",
      "地方激励措施表明与区域经济发展目标一致。"
    ],
    "dayNumber": 1,
    "isCompleted": false
  },
  {
    "id": 1406,
    "title": "市场时机的风险因素",
    "category": "房地产与商业",
    "subcategory": "市场分析",
    "description": "项目启动时机不佳可能导致表现不佳。考虑周期性风险，如经济衰退、季节性波动或影响需求的政策变化。",
    "shortDescription": "项目启动时机不佳可能导致表现不佳。",
    "examples": [
      "在旅游业低迷时期启动一个酒店项目可能会延迟创造就业。",
      "利率上调或建筑成本通胀可能会打乱预测。"
    ],
    "dayNumber": 1,
    "isCompleted": false
  },
  {
    "id": 1501,
    "title": "选址与可行性",
    "category": "房地产与商业",
    "subcategory": "项目开发周期",
    "description": "项目开发始于选择一个地点并评估其可行性。这包括土地收购、分区、公用设施接入和初步成本估算。",
    "shortDescription": "项目开发始于选择一个地点并评估其可行性。",
    "examples": [
      "一位房地产开发商选择了一个靠近交通路线的郊区地块，用于一个多功能项目。",
      "可行性研究表明，当地需求支持拟议的开发。"
    ],
    "dayNumber": 1,
    "isCompleted": false
  },
  {
    "id": 1502,
    "title": "规划与设计",
    "category": "房地产与商业",
    "subcategory": "项目开发周期",
    "description": "开发商聘请建筑师、工程师和顾问来设计项目。在此阶段准备场地规划、结构蓝图和美学设计。",
    "shortDescription": "开发商聘请建筑师、工程师和顾问来设计项目。",
    "examples": [
      "建筑师设计了一家拥有 250 间客房、活动空间和屋顶餐厅的酒店。",
      "土木工程师评估了场地的排水和环境影响。"
    ],
    "dayNumber": 1,
    "isCompleted": false
  },
  {
    "id": 1503,
    "title": "许可证和权利",
    "category": "房地产与商业",
    "subcategory": "项目开发周期",
    "description": "此阶段包括从地方和州当局获得许可证、执照和监管批准。这可能很耗时，但对于合法建设是必要的。",
    "shortDescription": "此阶段包括从地方和州当局获得许可证、执照和监管批准。",
    "examples": [
      "市规划委员会批准了住宅密度增加的分区。",
      "开发商获得了建筑许可证和消防安全许可。"
    ],
    "dayNumber": 1,
    "isCompleted": false
  },
  {
    "id": 1504,
    "title": "筹集资金和融资",
    "category": "房地产与商业",
    "subcategory": "项目开发周期",
    "description": "开发商从多种来源获得资金：股权、贷款以及可能还有 EB-5 资本。清晰的资本结构对于项目启动至关重要。",
    "shortDescription": "开发商从多种来源获得资金：股权、贷款以及可能还有 EB-5 资本。",
    "examples": [
      "EB-5 资金覆盖了项目成本的 30%，同时还有来自商业银行的优先贷款。",
      "投资者审查资本结构以评估财务可行性。"
    ],
    "dayNumber": 1,
    "isCompleted": false
  },
  {
    "id": 1505,
    "title": "施工阶段",
    "category": "房地产与商业",
    "subcategory": "项目开发周期",
    "description": "融资敲定后，项目进入施工阶段。这是大多数 EB-5 就业创造发生的地方，通过直接和间接就业。",
    "shortDescription": "融资敲定后，项目进入施工阶段。",
    "examples": [
      "为期 24 个月的建设计划雇佣了数百名建筑工人。",
      "供应商和分包商产生了额外的经济影响。"
    ],
    "dayNumber": 1,
    "isCompleted": false
  },
  {
    "id": 1506,
    "title": "运营与稳定",
    "category": "房地产与商业",
    "subcategory": "项目开发周期",
    "description": "施工结束后，项目出租、出售或投入运营。稳定化包括达到目标入住率或收入，这支持了 EB-5 就业创造的核实。",
    "shortDescription": "施工结束后，项目出租、出售或投入运营。",
    "examples": [
      "一个已完工的公寓大楼在六个月内达到了 90% 的入住率。",
      "一个零售中心与主力租户签订了长期租赁协议。"
    ],
    "dayNumber": 1,
    "isCompleted": false
  },
  {
    "id": 1507,
    "title": "退出和偿还投资者",
    "category": "房地产与商业",
    "subcategory": "项目开发周期",
    "description": "最后一个阶段是在满足创造就业和维持要求后偿还投资者。这通常通过再融资、资产出售或分配来完成。",
    "shortDescription": "最后一个阶段是在满足创造就业和维持要求后偿还投资者。",
    "examples": [
      "一个商业物业被出售给机构投资者，将资本返还给 EB-5 参与者。",
      "再融资使项目能够在 I-829 批准后偿还投资者。"
    ],
    "dayNumber": 1,
    "isCompleted": false
  },
  {
    "id": 1601,
    "title": "商业地产概览",
    "category": "房地产与商业",
    "subcategory": "商业与住宅",
    "description": "商业地产包括写字楼、购物中心、酒店、仓库和工业空间。这些项目通常涉及更高的资本、更长的时间线和更多的就业创造。",
    "shortDescription": "商业地产包括写字楼、购物中心、酒店、仓库和工业空间。",
    "examples": [
      "一位EB-5投资者帮助资助了一家拥有零售商店和会议设施的酒店。",
      "商业项目通常涉及更大的团队，从而促进了间接就业的创造。"
    ],
    "dayNumber": 1,
    "isCompleted": false
  },
  {
    "id": 1602,
    "title": "住宅房地产概览",
    "category": "房地产与商业",
    "subcategory": "商业与住宅",
    "description": "住宅物业包括公寓大楼、共管公寓和联排别墅。这些开发项目可能提供更快的建设时间和更稳定的入住率。",
    "shortDescription": "住宅物业包括公寓大楼、共管公寓和联排别墅。",
    "examples": [
      "一位投资者支持在一个不断发展的郊区建造一座拥有120个单元的公寓楼。",
      "住宅需求受到当地人口增长和住房短缺的推动。"
    ],
    "dayNumber": 1,
    "isCompleted": false
  },
  {
    "id": 1603,
    "title": "收入模式",
    "category": "房地产与商业",
    "subcategory": "商业与住宅",
    "description": "商业物业通常依赖于向企业出租空间，这可以产生高回报，但对市场周期敏感。住宅房地产从租金中产生收入，波动性较小。",
    "shortDescription": "商业物业通常依赖于向企业出租空间，这可以产生高回报，但对市场周期敏感。",
    "examples": [
      "市中心地区的办公空间租金高，但随经济状况波动。",
      "如果入住率保持强劲，公寓楼可以产生稳定的现金流。"
    ],
    "dayNumber": 1,
    "isCompleted": false
  },
  {
    "id": 1604,
    "title": "创造就业的考虑因素",
    "category": "房地产与商业",
    "subcategory": "商业与住宅",
    "description": "商业项目通常能创造更多的工作岗位，包括管理、零售、酒店和维护岗位。住宅项目通常产生的长期工作岗位较少，但建筑就业岗位较多。",
    "shortDescription": "商业项目通常能创造更多的工作岗位，包括管理、零售、酒店和维护岗位。",
    "examples": [
      "一个酒店项目长期雇佣厨师、接待员和维护人员。",
      "一个住宅开发项目主要在建设阶段创造就业岗位。"
    ],
    "dayNumber": 1,
    "isCompleted": false
  },
  {
    "id": 1605,
    "title": "退出策略",
    "category": "房地产与商业",
    "subcategory": "商业与住宅",
    "description": "商业退出可能涉及再融资或出售给机构买家。住宅项目通常将单个单位或整个建筑出售给当地投资者或基金。",
    "shortDescription": "商业退出可能涉及再融资或出售给机构买家。",
    "examples": [
      "一个商业购物广场被再融资以向投资者返还资本。",
      "一个住宅开发项目分阶段出售已完工的单位以收回投资。"
    ],
    "dayNumber": 1,
    "isCompleted": false
  },
  {
    "id": 1606,
    "title": "风险概况",
    "category": "房地产与商业",
    "subcategory": "商业与住宅",
    "description": "由于依赖租户租赁和经济状况，商业项目的风险可能更高。在强劲的住房市场中，住宅项目的风险可能较低，但回报也较低。",
    "shortDescription": "由于依赖租户租赁和经济状况，商业项目的风险可能更高。",
    "examples": [
      "一个位于 struggling metro area 的写字楼面临着高空置风险。",
      "郊区住房可能提供稳定的回报，但上行潜力有限。"
    ],
    "dayNumber": 1,
    "isCompleted": false
  },
  {
    "id": 1701,
    "title": "什么是EB-5商业计划？",
    "category": "房地产与商业",
    "subcategory": "EB-5商业计划",
    "description": "EB-5商业计划概述了投资者的资本将如何使用，以及项目将如何满足创造就业的要求。它必须遵守《Matter of Ho》，这是一项美国公民及移民服务局的先例，定义了商业计划的可信度。",
    "shortDescription": "EB-5商业计划概述了投资者的资本将如何使用，以及项目将如何满足创造就业的要求。",
    "examples": [
      "一份商业计划描述了一家新的连锁餐厅将如何创造15个全职工作岗位。",
      "该计划包括时间表、人员配置图和营销策略。"
    ],
    "dayNumber": 1,
    "isCompleted": false
  },
  {
    "id": 1702,
    "title": "遵守《Matter of Ho》",
    "category": "房地产与商业",
    "subcategory": "EB-5商业计划",
    "description": "要获得批准，EB-5商业计划必须满足美国公民及移民服务局在《Matter of Ho》下的标准，包括详细的招聘时间表、预算预测、市场分析和法律结构。",
    "shortDescription": "要获得批准，EB-5商业计划必须满足美国公民及移民服务局在《Matter of Ho》下的标准，包括详细的招聘时间表、预算预测...",
    "examples": [
      "一份计划包括5年财务预测和按部门划分的员工细分。",
      "未能显示资本使用与创造就业之间的直接联系可能导致被拒。"
    ],
    "dayNumber": 1,
    "isCompleted": false
  },
  {
    "id": 1703,
    "title": "合规计划的要素",
    "category": "房地产与商业",
    "subcategory": "EB-5商业计划",
    "description": "一份强有力的EB-5商业计划的关键组成部分包括：执行摘要、行业分析、运营策略、人员配置计划、市场需求、风险因素和财务预测。",
    "shortDescription": "一份强有力的EB-5商业计划的关键组成部分包括：执行摘要、行业分析、运营策略、人员配置计划、市场...",
    "examples": [
      "一个项目包括SWOT分析，以识别运营优势和风险。",
      "人员配置计划概述了前18个月内要填补的12个全职职位。"
    ],
    "dayNumber": 1,
    "isCompleted": false
  },
  {
    "id": 1704,
    "title": "经济报告的作用",
    "category": "房地产与商业",
    "subcategory": "EB-5商业计划",
    "description": "对于区域中心项目，经济报告包含在商业计划中，以使用美国公民及移民服务局批准的模型（如IMPLAN或RIMS II）计算创造的就业机会。",
    "shortDescription": "对于区域中心项目，经济报告包含在商业计划中，以使用美国公民及移民服务局批准的模型（如IMPLAN或RIMS II）计算创造的就业机会...",
    "examples": [
      "一份经济分析报告显示了一个建筑项目将如何创造150个直接和间接就业岗位。",
      "IMPLAN模型表明，每个EB-5投资者至少与10个工作岗位相关联。"
    ],
    "dayNumber": 1,
    "isCompleted": false
  },
  {
    "id": 1705,
    "title": "项目时间表和里程碑",
    "category": "房地产与商业",
    "subcategory": "EB-5商业计划",
    "description": "该计划必须显示一个现实的项目开发、创造就业和投资者参与的时间表。这有助于美国公民及移民服务局评估可行性以及是否符合创造就业的最后期限。",
    "shortDescription": "该计划必须显示一个现实的项目开发、创造就业和投资者参与的时间表。",
    "examples": [
      "该计划显示，建筑将于第三季度开始，第一批招聘将于第四季度进行。",
      "投资者资本计划在美国公民及移民服务局批准后60天内部署。"
    ],
    "dayNumber": 1,
    "isCompleted": false
  },
  {
    "id": 1706,
    "title": "EB-5文件之间的一致性",
    "category": "房地产与商业",
    "subcategory": "EB-5商业计划",
    "description": "商业计划必须与其他EB-5文件保持一致，包括I-526E表格、私募备忘录（PPM）和发行文件。差异可能导致延误或拒绝。",
    "shortDescription": "商业计划必须与其他EB-5文件保持一致，包括I-526E表格、私募备忘录（PPM）和发行文件...",
    "examples": [
      "商业计划中的人员配置图与I-526E表格中的创造就业数量相符。",
      "PPM和商业计划中资本结构的不匹配可能会引发RFE。"
    ],
    "dayNumber": 1,
    "isCompleted": false
  },
  {
    "id": 1801,
    "title": "佛罗里达州的酒店项目",
    "category": "房地产与商业",
    "subcategory": "案例研究",
    "description": "一组40名EB-5投资者资助了迈阿密附近的一家豪华度假村。区域中心将投资结构化为贷款。该项目超额完成了创造就业的目标，并在6年后返还了资本。",
    "shortDescription": "一组40名EB-5投资者资助了迈阿密附近的一家豪华度假村。",
    "examples": [
      "根据一份经济影响报告，每位投资者创造了14.2个工作岗位。",
      "投资者在稳定和再融资后获得了资本回报。"
    ],
    "dayNumber": 1,
    "isCompleted": false
  },
  {
    "id": 1802,
    "title": "俄亥俄州的农村制造设施",
    "category": "房地产与商业",
    "subcategory": "案例研究",
    "description": "一位直接投资者在一个被指定为TEA的农村小镇创办了一家小工厂。该项目创造了16个直接就业岗位，并满足了EB-5的维持要求，最终成功获得了I-829的批准。",
    "shortDescription": "一位直接投资者在一个被指定为TEA的农村小镇创办了一家小工厂。",
    "examples": [
      "该企业在生产和物流方面雇佣了3班工人。",
      "投资者积极管理运营，并在第一年后进行了扩张。"
    ],
    "dayNumber": 1,
    "isCompleted": false
  },
  {
    "id": 1803,
    "title": "加利福尼亚州的老年生活中心",
    "category": "房地产与商业",
    "subcategory": "案例研究",
    "description": "一个EB-5项目涉及在加利福尼亚州郊区开发一个老年生活社区。创造了100多个工作岗位，区域中心在5年后促成了全额还款。",
    "shortDescription": "一个EB-5项目涉及在加利福尼亚州郊区开发一个老年生活社区。",
    "examples": [
      "护士、厨房工作人员和管理人员构成了直接就业的核心。",
      "就业创造是通过直接和间接模型计算的。"
    ],
    "dayNumber": 1,
    "isCompleted": false
  },
  {
    "id": 1804,
    "title": "德克萨斯州的物流中心",
    "category": "房地产与商业",
    "subcategory": "案例研究",
    "description": "一个区域中心从EB-5投资者那里筹集了4000万美元，用于在德克萨斯州南部开发一个物流中心。尽管施工有所延误，但该项目按预算和时间完成了。",
    "shortDescription": "一个区域中心从EB-5投资者那里筹集了4000万美元，用于在德克萨斯州南部开发一个物流中心。",
    "examples": [
      "尽管时间表有变，但创造就业的缓冲机制使该项目得以保持合规。",
      "由于持续的就业追踪，美国公民及移民服务局批准了所有I-829申请。"
    ],
    "dayNumber": 1,
    "isCompleted": false
  },
  {
    "id": 1805,
    "title": "纽约的多功能城市项目",
    "category": "房地产与商业",
    "subcategory": "案例研究",
    "description": "一个备受瞩目的曼哈顿开发项目结合了办公、零售和住宅部分。EB-5投资者与机构股权和银行贷款一起参与。",
    "shortDescription": "一个备受瞩目的曼哈顿开发项目结合了办公、零售和住宅部分。",
    "examples": [
      "在项目的所有阶段创造了1000多个工作岗位。",
      "由于与大流行相关的租赁影响，投资者的退出时间表有所延迟。"
    ],
    "dayNumber": 1,
    "isCompleted": false
  },
  {
    "id": 1806,
    "title": "亚利桑那州的特许学校扩建",
    "category": "房地产与商业",
    "subcategory": "案例研究",
    "description": "EB-5资金支持了在凤凰城建造两个新的特许学校校区。该项目得到了州教育资金的支持，并创造了60多个直接就业岗位。",
    "shortDescription": "EB-5资金支持了在凤凰城建造两个新的特许学校校区。",
    "examples": [
      "教师、管理人员和设施工作人员计入创造就业。",
      "特许学校扩建项目在EB-5中越来越受欢迎。"
    ],
    "dayNumber": 1,
    "isCompleted": false
  },
  {
    "id": 1901,
    "title": "提交 I-526 或 I-526E 表格",
    "category": "移民与法律程序",
    "subcategory": "EB-5 申请流程",
    "description": "EB-5 流程始于提交 I-526（直接）或 I-526E（区域中心）表格。该申请显示了投资者的合法资金来源和创造就业的投资计划。",
    "shortDescription": "EB-5 流程始于提交 I-526（直接）或 I-526E（区域中心）表格。",
    "examples": [
      "投资者在 I-526 申请中包括银行记录、纳税申报表和全面的商业计划。",
      "对于区域中心项目，使用 I-526E 并包括中心的文件。"
    ],
    "dayNumber": 1,
    "isCompleted": false
  },
  {
    "id": 1902,
    "title": "美国公民及移民服务局审查和处理",
    "category": "移民与法律程序",
    "subcategory": "EB-5 申请流程",
    "description": "美国公民及移民服务局审查申请的资格、资金可追溯性和创造就业的策略。如果需要，他们可能会发出证据要求（RFE）或意向拒绝通知（NOID）。",
    "shortDescription": "美国公民及移民服务局审查申请的资格、资金可追溯性和创造就业的策略。",
    "examples": [
      "美国公民及移民服务局在 RFE 中要求澄清就业文件和时间表。",
      "投资者提交了额外的证据，证明了赠与的合法来源。"
    ],
    "dayNumber": 1,
    "isCompleted": false
  },
  {
    "id": 1903,
    "title": "批准和签证可用性",
    "category": "移民与法律程序",
    "subcategory": "EB-5 申请流程",
    "description": "一旦 I-526/I-526E 表格获得批准，投资者必须查看签证公告以确认其国家是否有可用的签证。如果当前可用，他们可以继续申请绿卡。",
    "shortDescription": "一旦 I-526/I-526E 表格获得批准，投资者必须查看签证公告以确认其国家是否有可用的签证。",
    "examples": [
      "一位印度投资者等待其优先日期生效后再继续。",
      "来自低需求国家的投资者可以在 I-526 批准后立即继续。"
    ],
    "dayNumber": 1,
    "isCompleted": false
  },
  {
    "id": 1904,
    "title": "身份调整或领事处理",
    "category": "移民与法律程序",
    "subcategory": "EB-5 申请流程",
    "description": "如果在美国，投资者提交 I-485 表格进行身份调整。如果在国外，他们通过美国大使馆使用 DS-260 进行领事处理申请。",
    "shortDescription": "如果在美国，投资者提交 I-485 表格进行身份调整。",
    "examples": [
      "一名在美国的 F-1 签证学生提交 I-485 以调整为 EB-5 身份。",
      "一位居住在国外的投资者在提交 DS-260 后安排了领事馆面试。"
    ],
    "dayNumber": 1,
    "isCompleted": false
  },
  {
    "id": 1905,
    "title": "有条件绿卡签发",
    "category": "移民与法律程序",
    "subcategory": "EB-5 申请流程",
    "description": "在调整或领事程序批准后，投资者将获得为期两年的有条件绿卡。他们必须在此期间达到投资和创造就业的目标。",
    "shortDescription": "在调整或领事程序批准后，投资者将获得为期两年的有条件绿卡。",
    "examples": [
      "一位投资者获得有条件绿卡并与家人一起搬到美国。",
      "投资者获得有条件绿卡并搬迁以管理业务。",
      "两年期从美国入境或调整批准之日开始。",
      "两年期从入境或调整批准之日开始。"
    ],
    "dayNumber": 1,
    "isCompleted": false
  },
  {
    "id": 1906,
    "title": "提交 I-829 表格以取消条件",
    "category": "移民与法律程序",
    "subcategory": "EB-5 申请流程",
    "description": "在获得有条件绿卡第二周年之前的 90 天内，投资者必须提交 I-829 表格，以证明投资得以维持并创造了就业机会。",
    "shortDescription": "在获得有条件绿卡第二周年之前的 90 天内，投资者必须提交 I-829 表格，以证明...",
    "examples": [
      "投资者在 I-829 中包括了工资记录、税务文件和财务报表。",
      "未及时提交 I-829 可能导致失去永久居留权。"
    ],
    "dayNumber": 1,
    "isCompleted": false
  },
  {
    "id": 2001,
    "title": "表格I-526 / I-526E – 移民申请",
    "category": "移民与法律程序",
    "subcategory": "EB-5申请表格",
    "description": "表格I-526（或对于区域中心投资者为I-526E）启动EB-5程序。它证明了投资者的资格、资金的合法来源以及创造就业的投资计划。",
    "shortDescription": "表格I-526（或对于区域中心投资者为I-526E）启动EB-5程序。",
    "examples": [
      "一位直接EB-5投资者提交表格I-526，并附上在餐饮业投资的证明。",
      "一位区域中心参与者提交表格I-526E，并附上该项目的经济报告。"
    ],
    "dayNumber": 1,
    "isCompleted": false
  },
  {
    "id": 2002,
    "title": "表格I-485 – 调整身份",
    "category": "移民与法律程序",
    "subcategory": "EB-5申请表格",
    "description": "如果投资者已经在美国，他们在I-526批准且有可用签证后，提交表格I-485以将其身份调整为合法永久居民。",
    "shortDescription": "如果投资者已经在美国，他们在I-526批准且有可用签证后，提交表格I-485以将其身份调整为合法永久居民...",
    "examples": [
      "一位持有H-1B签证的投资者使用I-485转为EB-5有条件居民身份。",
      "表格I-485包括生物特征、体检和个人历史详情。"
    ],
    "dayNumber": 1,
    "isCompleted": false
  },
  {
    "id": 2003,
    "title": "表格DS-260 – 领事处理",
    "category": "移民与法律程序",
    "subcategory": "EB-5申请表格",
    "description": "居住在美国境外的投资者在I-526/I-526E批准且有可用签证后，使用表格DS-260在美国领事馆申请移民签证。",
    "shortDescription": "居住在美国境外的投资者。",
    "examples": [
      "一位在印度的投资者填写DS-260以在美国大使馆安排签证面试。",
      "表格DS-260通过国家签证中心门户网站在线提交。"
    ],
    "dayNumber": 1,
    "isCompleted": false
  },
  {
    "id": 2004,
    "title": "表格I-829 – 取消条件",
    "category": "移民与法律程序",
    "subcategory": "EB-5申请表格",
    "description": "在两年有条件期满前的90天内提交，表格I-829请求取消条件，并证明投资者满足了创造就业和维持投资的要求。",
    "shortDescription": "在两年有条件期满前的90天内提交，表格I-829请求取消条件，并证明投资者...",
    "examples": [
      "I-829包括工资记录、营业执照和投资银行对账单。",
      "一旦批准，投资者及其家人将获得有效期为10年的永久绿卡。"
    ],
    "dayNumber": 1,
    "isCompleted": false
  },
  {
    "id": 2005,
    "title": "表格I-956K – 代理人注册",
    "category": "移民与法律程序",
    "subcategory": "EB-5申请表格",
    "description": "任何作为EB-5项目推广人、中间人或代理人的人都必须提交表格I-956K，以披露他们与区域中心的关系，并确认遵守美国公民及移民服务局的规定。",
    "shortDescription": "任何作为EB-5项目推广人、中间人或代理人的人都必须提交表格I-956K，以披露他们与区域中心的关系...",
    "examples": [
      "与区域中心合作的营销代理人提交I-956K以在美国公民及移民服务局注册。",
      "未提交I-956K可能导致与该代理人相关的投资者申请被取消资格。"
    ],
    "dayNumber": 1,
    "isCompleted": false
  },
  {
    "id": 2006,
    "title": "表格I-956F – 项目申请",
    "category": "移民与法律程序",
    "subcategory": "EB-5申请表格",
    "description": "表格I-956F必须由区域中心为每个EB-5项目发行提交。它包含该项目的商业计划、经济报告、证券文件和创造就业模型。",
    "shortDescription": "表格I-956F必须由区域中心为每个EB-5项目发行提交。",
    "examples": [
      "一个区域中心在投资者可以提交I-526E之前，提交I-956F并附上一整套项目文件。",
      "项目必须在I-956F下获得批准，投资者才能继续。"
    ],
    "dayNumber": 1,
    "isCompleted": false
  },
  {
    "id": 2102,
    "title": "有条件居民的权利",
    "category": "移民与法律程序",
    "subcategory": "绿卡程序",
    "description": "EB-5有条件绿卡持有人拥有在美国生活、工作和学习的全部权利。他们可以旅行、开办企业，并让子女入读公立学校。",
    "shortDescription": "EB-5有条件绿卡持有人拥有在美国生活、工作和学习的全部权利。",
    "examples": [
      "投资者的配偶开办了一家企业，而他们的孩子在美国一所大学上学。",
      "一旦获得有条件身份，该家庭就不受签证限制。"
    ],
    "dayNumber": 1,
    "isCompleted": false
  },
  {
    "id": 2103,
    "title": "通过表格I-829取消条件",
    "category": "移民与法律程序",
    "subcategory": "绿卡程序",
    "description": "要将有条件绿卡转换为永久绿卡，投资者必须在卡到期前的90天窗口内提交表格I-829。这证明了投资的持续性和创造就业。",
    "shortDescription": "要将有条件绿卡转换为永久绿卡，投资者必须在卡到期前的90天窗口内提交表格I-829...",
    "examples": [
      "投资者在表格I-829中提交了工资单、税务记录和资本使用证明。",
      "一旦批准，将签发一张为期10年的无条件绿卡。"
    ],
    "dayNumber": 1,
    "isCompleted": false
  },
  {
    "id": 2104,
    "title": "10年绿卡（永久居留权）",
    "category": "移民与法律程序",
    "subcategory": "绿卡程序",
    "description": "一旦表格I-829获得批准，投资者及其合格的家庭成员将获得一张有效期为10年的永久绿卡。它是可续签的，并作为合法永久居留权的证明。",
    "shortDescription": "一旦表格I-829获得批准，投资者及其合格的家庭成员将获得一张有效期为10年的永久绿卡。",
    "examples": [
      "投资者获得一张10年绿卡，不再需要证明创造就业。",
      "家庭成员获得相同的永久身份，并享有全部居留权。"
    ],
    "dayNumber": 1,
    "isCompleted": false
  },
  {
    "id": 2105,
    "title": "维持绿卡身份",
    "category": "移民与法律程序",
    "subcategory": "绿卡程序",
    "description": "为了保持绿卡身份，居民不得放弃在美国居住的意图，避免长时间缺席，并遵守税务和居住义务。",
    "shortDescription": "为了保持绿卡身份，居民不得放弃在美国居住的意图，避免长时间缺席，并遵守税务和...",
    "examples": [
      "在国外停留超过6个月可能会引发放弃身份的担忧。",
      "提交美国纳税申报表和与美国保持联系有助于保留身份。"
    ],
    "dayNumber": 1,
    "isCompleted": false
  },
  {
    "id": 2106,
    "title": "获得美国公民身份的资格",
    "category": "移民与法律程序",
    "subcategory": "绿卡程序",
    "description": "在合法永久居留5年后（包括有条件身份），如果EB-5投资者满足实际居住、语言和公民知识要求，他们可以申请入籍。",
    "shortDescription": "在合法永久居留5年后（包括有条件身份），如果EB-5投资者满足...",
    "examples": [
      "一位投资者在获得有条件绿卡五年后申请美国公民身份。",
      "入籍过程包括背景调查和公民身份面试。"
    ],
    "dayNumber": 1,
    "isCompleted": false
  },
  {
    "id": 2201,
    "title": "身份调整 (AOS) 概览",
    "category": "移民与法律程序",
    "subcategory": "身份调整与领事处理",
    "description": "身份调整允许已经在美国的 EB-5 投资者通过提交 I-485 表格，从非移民身份转变为移民身份，而无需离开该国。",
    "shortDescription": "身份调整允许已经在美国的 EB-5 投资者。",
    "examples": [
      "一名 F-1 学生在 I-526 批准后提交 I-485，成为有条件绿卡持有人。",
      "投资者在处理期间留在美国，并获得工作/旅行许可。"
    ],
    "dayNumber": 1,
    "isCompleted": false
  },
  {
    "id": 2202,
    "title": "领事处理概览",
    "category": "移民与法律程序",
    "subcategory": "身份调整与领事处理",
    "description": "领事处理适用于居住在美国境外的 EB-5 投资者。在 I-526/I-526E 批准后，他们通过其本国的美国领事馆申请移民签证。",
    "shortDescription": "领事处理适用于居住在美国境外的 EB-5 投资者。",
    "examples": [
      "一位在中国的投资者在美国驻广州总领事馆安排了签证面试。",
      "在 DS-260 批准后，投资者获得签证并作为有条件居民进入美国。"
    ],
    "dayNumber": 1,
    "isCompleted": false
  },
  {
    "id": 2203,
    "title": "AOS 处理时间线和好处",
    "category": "移民与法律程序",
    "subcategory": "身份调整与领事处理",
    "description": "身份调整通常可以更快地获得工作和旅行授权 (EAD/AP)，并且避免了国际旅行的需要。处理时间因美国公民及移民服务局的工作量而异。",
    "shortDescription": "身份调整通常可以更快地获得工作和旅行授权 (EAD/AP)，并且避免了国际旅行的需要。",
    "examples": [
      "一名学生在提交 I-485 表格后的 90 天内收到了 EAD 卡。",
      "提前假释允许投资者在 AOS 待决期间出国旅行。"
    ],
    "dayNumber": 1,
    "isCompleted": false
  },
  {
    "id": 2204,
    "title": "领事面试和进入美国",
    "category": "移民与法律程序",
    "subcategory": "身份调整与领事处理",
    "description": "在领事处理中，申请人必须在国外参加签证面试。一旦批准，他们进入美国并在抵达时激活他们的 EB-5 绿卡身份。",
    "shortDescription": "在领事处理中，申请人必须在国外参加签证面试。",
    "examples": [
      "签证盖章是在体检和背景调查后由领事馆签发的。",
      "绿卡在投资者通过入境口岸进入美国后邮寄。"
    ],
    "dayNumber": 1,
    "isCompleted": false
  },
  {
    "id": 2205,
    "title": "在 AOS 和领事处理之间选择的因素",
    "category": "移民与法律程序",
    "subcategory": "身份调整与领事处理",
    "description": "在身份调整和领事处理之间进行选择取决于当前的位置、签证可用性、旅行需求和移民历史。通常需要法律咨询。",
    "shortDescription": "在身份调整和领事处理之间进行选择取决于当前的位置、签证可用性、旅行需求和移民...",
    "examples": [
      "由于意图问题，持有 B-1 签证的商务访客可能没有资格获得 AOS。",
      "具有双重意图的 H-1B 工作人员可以安全地使用 AOS，同时保持就业。"
    ],
    "dayNumber": 1,
    "isCompleted": false
  },
  {
    "id": 2206,
    "title": "处理期间的旅行注意事项",
    "category": "移民与法律程序",
    "subcategory": "身份调整与领事处理",
    "description": "申请 AOS 的人必须避免在没有提前假释的情况下进行国际旅行。领事申请人应在签证签发前留在国外，以避免被拒。",
    "shortDescription": "申请 AOS 的人必须避免在没有提前假释的情况下进行国际旅行。",
    "examples": [
      "没有旅行证件就旅行的 AOS 申请人有放弃申请的风险。",
      "领事处理需要在等待海外面试安排时保持耐心。"
    ],
    "dayNumber": 1,
    "isCompleted": false
  },
  {
    "id": 2301,
    "title": "移民律师的角色",
    "category": "移民与法律程序",
    "subcategory": "移民律师与顾问",
    "description": "移民律师提供法律建议，准备和提交EB-5表格，并帮助确保遵守美国公民及移民服务局的规定。他们是持牌和受监管的专业人士，在移民法方面拥有专业知识。",
    "shortDescription": "移民律师提供法律建议，准备和提交EB-5表格，并帮助确保遵守美国公民及移民服务局的规定。",
    "examples": [
      "律师起草I-526表格并审查商业计划以确保其符合《Matter of Ho》。",
      "律师与美国公民及移民服务局沟通并回应证据要求（RFE）。"
    ],
    "dayNumber": 1,
    "isCompleted": false
  },
  {
    "id": 2302,
    "title": "选择合格的EB-5律师",
    "category": "移民与法律程序",
    "subcategory": "移民律师与顾问",
    "description": "投资者应选择具有EB-5经验、良好推荐信和批准记录的律师。避免选择通才或对EB-5规则和合规性没有深入了解的律师。",
    "shortDescription": "投资者应选择具有EB-5经验、良好推荐信和批准记录的律师。",
    "examples": [
      "经验丰富的EB-5律师有助于避免在创造就业文件方面的常见错误。",
      "检查客户推荐信和批准历史可以帮助评估可信度。"
    ],
    "dayNumber": 1,
    "isCompleted": false
  },
  {
    "id": 2303,
    "title": "移民代理和顾问的角色",
    "category": "移民与法律程序",
    "subcategory": "移民律师与顾问",
    "description": "移民代理和顾问协助项目选择、文件准备以及与法律团队的协调。除非他们也是律师，否则他们无权提供法律建议。",
    "shortDescription": "移民代理和顾问协助项目选择、文件准备以及与法律团队的协调。",
    "examples": [
      "代理人帮助投资者评估区域中心项目并提交财务记录。",
      "非律师顾问不能提供法律意见或在美国公民及移民服务局面前代表客户。"
    ],
    "dayNumber": 1,
    "isCompleted": false
  },
  {
    "id": 2304,
    "title": "代理人注册要求 (I-956K)",
    "category": "移民与法律程序",
    "subcategory": "移民律师与顾问",
    "description": "根据《EB-5改革与诚信法案》，所有推广EB-5项目的代理人都必须向美国公民及移民服务局提交I-956K表格。这确保了投资过程的透明度和问责制。",
    "shortDescription": "根据《EB-5改革与诚信法案》，所有推广EB-5项目的代理人都必须向美国公民及移民服务局提交I-956K表格。",
    "examples": [
      "推广EB-5项目的顾问必须在向投资者营销前通过I-956K注册。",
      "未注册可能会导致投资者的申请被取消资格。"
    ],
    "dayNumber": 1,
    "isCompleted": false
  },
  {
    "id": 2305,
    "title": "避免欺诈性顾问",
    "category": "移民与法律程序",
    "subcategory": "移民律师与顾问",
    "description": "投资者应警惕未注册的代理人、夸大的声明或成功的保证。只有持牌律师才能处理法律文件和策略。",
    "shortDescription": "投资者应警惕未注册的代理人、夸大的声明或成功的保证。",
    "examples": [
      "承诺保证获得绿卡的代理人很可能违反了EB-5法律。",
      "投资者在聘用前会检查顾问的I-956K注册和法律背景。"
    ],
    "dayNumber": 1,
    "isCompleted": false
  },
  {
    "id": 2306,
    "title": "与专业团队合作",
    "category": "移民与法律程序",
    "subcategory": "移民律师与顾问",
    "description": "成功的EB-5申请人通常与包括律师、财务规划师、项目分析师和翻译在内的专业团队合作，以确保准确性和完整性。",
    "shortDescription": "成功的EB-5申请人通常与包括律师、财务规划师、项目分析师和...",
    "examples": [
      "投资者的团队包括一名移民律师、一名注册会计师和一名EB-5顾问。",
      "合作的方式确保了法律合规和适当的资金文件。"
    ],
    "dayNumber": 1,
    "isCompleted": false
  },
  {
    "id": 2401,
    "title": "创造就业不足",
    "category": "移民与法律程序",
    "subcategory": "常见的EB-5问题与拒绝",
    "description": "未能创造至少10个全职合格工作岗位是EB-5申请被拒的主要原因之一，尤其是在I-829阶段。",
    "shortDescription": "未能创造至少10个全职合格工作岗位是EB-5申请被拒的主要原因之一，尤其是在I-829阶段。",
    "examples": [
      "一个项目预计每位投资者创造12个工作岗位，但最终只创造了8个，导致被拒。",
      "缺乏工资记录或可信的经济模型可能会引发与工作相关的RFE。"
    ],
    "dayNumber": 1,
    "isCompleted": false
  },
  {
    "id": 2402,
    "title": "资金来源不明确或无法核实",
    "category": "移民与法律程序",
    "subcategory": "常见的EB-5问题与拒绝",
    "description": "美国公民及移民服务局要求详细记录投资者如何合法获得和转移资金。任何缺口、不一致或可疑的交易都可能导致被拒。",
    "shortDescription": "美国公民及移民服务局要求详细记录投资者如何合法获得和转移资金。",
    "examples": [
      "一位投资者未能记录从一个离岸账户收到的大额电汇。",
      "缺失的纳税申报表或销售契约引发了对资金合法性的担忧。"
    ],
    "dayNumber": 1,
    "isCompleted": false
  },
  {
    "id": 2403,
    "title": "不当使用托管或贷款条款",
    "category": "移民与法律程序",
    "subcategory": "常见的EB-5问题与拒绝",
    "description": "保证资本回报或将投资与还款时间表挂钩的协议违反了EB-5的“风险投资”规则，并会导致美国公民及移民服务局的拒绝。",
    "shortDescription": "保证资本回报或将投资与还款时间表挂钩的协议违反了EB-5的“风险投资”规则，并会导致美国公民及移民服务局的...",
    "examples": [
      "一份附带协议承诺在五年内返还资本，无论是否创造了就业机会。",
      "投资者的资金从未离开托管账户，因此不被视为处于风险之中。"
    ],
    "dayNumber": 1,
    "isCompleted": false
  },
  {
    "id": 2404,
    "title": "商业计划不足",
    "category": "移民与法律程序",
    "subcategory": "常见的EB-5问题与拒绝",
    "description": "缺乏可信度、细节或创造就业策略的商业计划可能无法满足《Matter of Ho》的标准，并导致在I-526或I-829阶段被拒。",
    "shortDescription": "缺乏可信度、细节或创造就业策略的商业计划可能无法满足《Matter of Ho》的标准，并导致在I-526或I-829阶段被拒...",
    "examples": [
      "该计划没有显示具体的招聘时间表或雇佣结构。",
      "预计的就业岗位与资本部署没有明确的联系。"
    ],
    "dayNumber": 1,
    "isCompleted": false
  },
  {
    "id": 2405,
    "title": "提交晚或错过",
    "category": "移民与法律程序",
    "subcategory": "常见的EB-5问题与拒绝",
    "description": "未能在有条件绿卡到期前的90天内提交I-829表格可能导致失去居留权和被拒，即使该项目满足了所有其他要求。",
    "shortDescription": "未能在有条件绿卡到期前的90天内提交I-829表格可能导致失去居留权和被拒，即使该项目满足了所有其他要求...",
    "examples": [
      "一位投资者错过了I-829的截止日期，并失去了合法永久居民身份。",
      "即使是一个强有力的案例，如果提交晚了或缺乏有效的解释，也可能被拒。"
    ],
    "dayNumber": 1,
    "isCompleted": false
  },
  {
    "id": 2406,
    "title": "欺诈或虚假陈述",
    "category": "移民与法律程序",
    "subcategory": "常见的EB-5问题与拒绝",
    "description": "在EB-5过程的任何部分提供虚假文件或歪曲事实都可能导致申请被拒、永久不得入境和法律后果。",
    "shortDescription": "在EB-5过程的任何部分提供虚假文件或歪曲事实都可能导致申请被拒、永久...",
    "examples": [
      "一位投资者声称创造了就业机会，后来被美国公民及移民服务局审计证明是伪造的。",
      "伪造收入报表导致被永久禁止进入美国。"
    ],
    "dayNumber": 1,
    "isCompleted": false
  },
  {
    "id": 2501,
    "title": "配偶和子女的资格",
    "category": "移民与法律程序",
    "subcategory": "通过EB-5的家庭移民",
    "description": "EB-5项目允许投资者的配偶和21岁以下的未婚子女作为衍生受益人获得有条件绿卡。",
    "shortDescription": "EB-5项目允许投资者的配偶和21岁以下的未婚子女作为衍生受益人获得有条件绿卡...",
    "examples": [
      "一位投资者与他们的配偶和两个未成年子女一起申请，他们都获得了绿卡。",
      "每个家庭成员都包含在同一份I-526或I-526E申请中。"
    ],
    "dayNumber": 1,
    "isCompleted": false
  },
  {
    "id": 2502,
    "title": "家庭的教育和工作权利",
    "category": "移民与法律程序",
    "subcategory": "通过EB-5的家庭移民",
    "description": "获得绿卡的家庭成员可以在公立或私立学校学习，并有资格在美国工作，无需额外许可。",
    "shortDescription": "获得绿卡的家庭成员可以在公立或私立学校学习，并有资格在美国工作。",
    "examples": [
      "一位EB-5投资者的孩子在一所州立大学就读，并有资格享受州内学费。",
      "投资者的配偶在获得绿卡后开始在一家医疗诊所工作。"
    ],
    "dayNumber": 1,
    "isCompleted": false
  },
  {
    "id": 2503,
    "title": "维持受抚养人身份",
    "category": "移民与法律程序",
    "subcategory": "通过EB-5的家庭移民",
    "description": "子女必须在签证签发时保持未婚且未满21岁，才有资格作为受抚养人。《儿童身份保护法》（CSPA）可能有助于在延误的情况下保留资格。",
    "shortDescription": "子女必须在签证签发时保持未婚且未满21岁，才有资格作为受抚养人。",
    "examples": [
      "一个孩子在申请处理期间年满21岁，但根据CSPA仍然有资格。",
      "如果孩子结婚，他们将失去作为衍生受益人的资格。"
    ],
    "dayNumber": 1,
    "isCompleted": false
  },
  {
    "id": 2504,
    "title": "家庭的永久居留权",
    "category": "移民与法律程序",
    "subcategory": "通过EB-5的家庭移民",
    "description": "在I-829表格获得批准后，所有符合条件的家庭成员都将获得无条件绿卡，并独立于主要投资者保留永久居留权。",
    "shortDescription": "在I-829表格获得批准后，所有符合条件的家庭成员都将获得无条件绿卡，并独立于主要投资者保留永久居留权...",
    "examples": [
      "在I-829批准后，投资者的配偶和子女获得了10年绿卡。",
      "家庭成员无需单独重新申请——他们都包含在I-829中。"
    ],
    "dayNumber": 1,
    "isCompleted": false
  },
  {
    "id": 2506,
    "title": "未来的家庭担保选项",
    "category": "移民与法律程序",
    "subcategory": "通过EB-5的家庭移民",
    "description": "一旦EB-5投资者成为永久居民或公民，他们可以通过基于家庭的移民渠道担保其他亲属，如父母、成年子女或兄弟姐妹。",
    "shortDescription": "一旦EB-5投资者成为永久居民或公民，他们可以通过基于家庭的移民渠道担保其他亲属，如父母、成年子女或...",
    "examples": [
      "一位入籍的投资者为他们的年迈父母提交了移民申请。",
      "家庭担保不属于EB-5的一部分，但可以在获得绿卡或公民身份后进行。"
    ],
    "dayNumber": 1,
    "isCompleted": false
  },
  {
    "id": 2601,
    "title": "商业失败的风险",
    "category": "风险管理",
    "subcategory": "EB-5 投资风险",
    "description": "EB-5 投资与其他任何商业投资一样，都存在风险。如果企业失败，投资者可能会失去资本和获得永久居留权的资格。",
    "shortDescription": "EB-5 投资与其他任何商业投资一样，都存在风险。",
    "examples": [
      "一家餐厅因位置不佳和市场条件恶劣而倒闭，未能创造就业机会。",
      "没有证明成功的投资结果，投资者无法取消条件。"
    ],
    "dayNumber": 1,
    "isCompleted": false
  },
  {
    "id": 2602,
    "title": "创造就业不足",
    "category": "风险管理",
    "subcategory": "EB-5 投资风险",
    "description": "如果一个项目未能为每位投资者创造或维持至少 10 个全职工作岗位，美国公民及移民服务局可能会拒绝 I-829 申请，并且不会授予永久居留权。",
    "shortDescription": "如果一个项目未能为每位投资者创造或维持至少 10 个全职工作岗位，美国公民及移民服务局可能会拒绝 I-829 申请，并且不会授予永久居留权...",
    "examples": [
      "施工延误阻碍了在有条件期内创造就业。",
      "表现不佳导致在记录工作岗位前裁员。"
    ],
    "dayNumber": 1,
    "isCompleted": false
  },
  {
    "id": 2603,
    "title": "项目延误或取消",
    "category": "风险管理",
    "subcategory": "EB-5 投资风险",
    "description": "由于许可问题、融资缺口或外部经济因素，开发项目可能会面临延误，这可能会影响 EB-5 的时间表和合规性。",
    "shortDescription": "由于许可问题、融资缺口或外部经济因素，开发项目可能会面临延误，这可能会影响 EB-5...",
    "examples": [
      "由于分区争议，一个酒店项目被推迟，将创造就业的时间推迟到要求的窗口之外。",
      "由于施工未达到工作里程碑，投资者的 I-829 提交被推迟。"
    ],
    "dayNumber": 1,
    "isCompleted": false
  },
  {
    "id": 2604,
    "title": "签证积压和国家上限",
    "category": "风险管理",
    "subcategory": "EB-5 投资风险",
    "description": "来自 EB-5 需求量大的国家的申请人可能会因每个国家的年度签证限制而面临漫长的等待期，这可能会延迟绿卡的签发，即使在投资批准之后也是如此。",
    "shortDescription": "来自 EB-5 需求量大的国家的申请人可能会因每个国家的年度签证限制而面临漫长的等待期，这可能会延迟绿卡...",
    "examples": [
      "由于超额认购，来自印度和中国的投资者通常会经历多年的延误。",
      "在等待签证号码可用时，孩子的超龄风险会增加。"
    ],
    "dayNumber": 1,
    "isCompleted": false
  },
  {
    "id": 2605,
    "title": "欺诈或管理不善的风险",
    "category": "风险管理",
    "subcategory": "EB-5 投资风险",
    "description": "投资者可能容易受到不诚实的项目赞助商或未注册的代理人的影响。欺诈或管理不善的项目可能导致财务损失和申请被拒。",
    "shortDescription": "投资者可能容易受到不诚实的项目赞助商或未注册的代理人的影响。",
    "examples": [
      "杰伊峰案件涉及滥用投资者资金，并导致了重大的美国公民及移民服务局改革。",
      "投资者在不知情的情况下加入了一个工作岗位预测虚高且执行不力的项目。"
    ],
    "dayNumber": 1,
    "isCompleted": false
  },
  {
    "id": 2606,
    "title": "经济和政治风险",
    "category": "风险管理",
    "subcategory": "EB-5 投资风险",
    "description": "市场低迷、利率变化、通货膨胀或移民政策变化都可能影响 EB-5 投资，无论是财务上还是程序上。",
    "shortDescription": "市场低迷、利率变化、通货膨胀或移民政策变化都可能影响 EB-5 投资，无论是财务上还是...",
    "examples": [
      "经济衰退减少了酒店收入，限制了创造就业和投资者回报。",
      "EB-5 重新授权的立法延误造成了项目的不确定性。"
    ],
    "dayNumber": 1,
    "isCompleted": false
  },
  {
    "id": 2701,
    "title": "了解项目结构",
    "category": "风险管理",
    "subcategory": "尽职调查流程",
    "description": "在投资之前，EB-5申请人应该了解项目的结构——谁是开发商，资金如何使用，以及各方扮演的角色。",
    "shortDescription": "在投资之前，EB-5申请人应该了解项目的结构——谁是开发商，资金如何使用，以及...",
    "examples": [
      "一位投资者审查了项目的组织结构图和资本结构图。",
      "一个信誉良好、有明确业绩记录的开发商可以降低项目风险。"
    ],
    "dayNumber": 1,
    "isCompleted": false
  },
  {
    "id": 2702,
    "title": "评估区域中心资质",
    "category": "风险管理",
    "subcategory": "尽职调查流程",
    "description": "审查赞助该项目的区域中心的经验、批准历史和诚信度。强有力的合规记录和I-829批准率是关键指标。",
    "shortDescription": "审查赞助该项目的区域中心的经验、批准历史和诚信度。",
    "examples": [
      "一个拥有数百份成功申请的区域中心更可靠。",
      "投资者要求提供过去项目创造就业和资本回报的历史记录。"
    ],
    "dayNumber": 1,
    "isCompleted": false
  },
  {
    "id": 2703,
    "title": "审查经济报告",
    "category": "风险管理",
    "subcategory": "尽职调查流程",
    "description": "第三方经济影响报告有助于确定创造就业的预测是否现实，并且是否基于合理的建模技术。",
    "shortDescription": "第三方经济影响报告有助于确定创造就业的预测是否现实，并且是否基于合理的建模技术。",
    "examples": [
      "IMPLAN报告根据1亿美元的建设支出预测了创造的就业岗位。",
      "投资者确保就业缓冲超过10个工作岗位的最低要求。"
    ],
    "dayNumber": 1,
    "isCompleted": false
  },
  {
    "id": 2704,
    "title": "法律和财务审查",
    "category": "风险管理",
    "subcategory": "尽职调查流程",
    "description": "彻底的法律和财务审查有助于发现潜在的危险信号。投资者应聘请律师和财务顾问来评估发行文件和托管安排。",
    "shortDescription": "彻底的法律和财务审查有助于发现潜在的危险信号。",
    "examples": [
      "律师审查PPM和托管协议，以核实资金流向和风险披露。",
      "财务专家检查回报模型是否现实且符合SEC规定。"
    ],
    "dayNumber": 1,
    "isCompleted": false
  },
  {
    "id": 2705,
    "title": "对赞助商进行背景调查",
    "category": "风险管理",
    "subcategory": "尽职调查流程",
    "description": "对EB-5项目的开发商、普通合伙人或经理进行背景调查，以查明诉讼历史、破产或其他危险信号。",
    "shortDescription": "对EB-5项目的开发商、普通合伙人或经理进行背景调查，以查明诉讼历史...",
    "examples": [
      "背景调查显示，一位负责人之前曾参与过一个失败的EB-5项目。",
      "投资者核实所有关键方都处于良好的法律地位。"
    ],
    "dayNumber": 1,
    "isCompleted": false
  },
  {
    "id": 2706,
    "title": "评估退出策略",
    "category": "风险管理",
    "subcategory": "尽职调查流程",
    "description": "明确定义的退出策略为投资者提供了何时以及如何获得资本回报的路线图。寻找现实的时间表和有市场支持的预测。",
    "shortDescription": "明确定义的退出策略为投资者提供了何时以及如何获得资本回报的路线图。",
    "examples": [
      "该计划包括在第六年进行一次预期的再融资或房产出售。",
      "含糊或过于乐观的退出语言可能预示着潜在的风险。"
    ],
    "dayNumber": 1,
    "isCompleted": false
  },
  {
    "id": 2801,
    "title": "识别危险信号",
    "category": "风险管理",
    "subcategory": "防欺诈",
    "description": "投资者应警惕潜在欺诈的迹象，例如不切实际的回报承诺、缺乏透明度、未注册的代理人或无法核实的项目细节。",
    "shortDescription": "投资者应警惕潜在欺诈的迹象，例如不切实际的回报承诺、缺乏透明度、未注册的代理人或...",
    "examples": [
      "一个项目既保证移民成功又保证资本回报——这是一个直接的危险信号。",
      "该区域中心拒绝披露详细的财务或所有权结构。"
    ],
    "dayNumber": 1,
    "isCompleted": false
  },
  {
    "id": 2802,
    "title": "核实代理人和项目注册",
    "category": "风险管理",
    "subcategory": "防欺诈",
    "description": "投资者应确保他们的项目与美国公民及移民服务局批准的区域中心相关联，并且任何中介机构都已提交I-956K表格向美国公民及移民服务局注册。",
    "shortDescription": "投资者应确保他们的项目与美国公民及移民服务局批准的区域中心相关联，并且任何中介机构都已提交I-956K表格...",
    "examples": [
      "投资者在美国公民及移民服务局的网站上查看该区域中心的指定。",
      "代理人在提供EB-5服务前出示其I-956K确认函。"
    ],
    "dayNumber": 1,
    "isCompleted": false
  },
  {
    "id": 2803,
    "title": "要求托管账户透明",
    "category": "风险管理",
    "subcategory": "防欺诈",
    "description": "托管账户有助于保护投资者资本。投资者应要求提供有关托管代理人、释放条件和法律监督的文件。",
    "shortDescription": "托管账户有助于保护投资者资本。",
    "examples": [
      "投资者收到一份托管协议副本，其中概述了在I-526批准后释放的条件。",
      "第三方托管经理确认对资金使用的控制。"
    ],
    "dayNumber": 1,
    "isCompleted": false
  },
  {
    "id": 2804,
    "title": "仔细审查发行文件",
    "category": "风险管理",
    "subcategory": "防欺诈",
    "description": "彻底审查私募备忘录（PPM）、认购协议和商业计划。所有披露、风险和条款都必须清晰、现实。",
    "shortDescription": "彻底审查私募备忘录（PPM）、认购协议和商业计划。",
    "examples": [
      "律师审查PPM并标记出创造就业模型中的不一致之处。",
      "投资者核实资本偿还条款是否符合EB-5法规。"
    ],
    "dayNumber": 1,
    "isCompleted": false
  },
  {
    "id": 2805,
    "title": "使用独立的法律和财务顾问",
    "category": "风险管理",
    "subcategory": "防欺诈",
    "description": "与项目无关的独立顾问可以提供无偏见的意见并发现欺诈风险。投资者应避免仅依赖项目代表。",
    "shortDescription": "与项目无关的独立顾问可以提供无偏见的意见并发现欺诈风险。",
    "examples": [
      "一位无关联的移民律师审查是否符合美国公民及移民服务局的要求。",
      "一位独立的注册会计师评估财务预测和资金流向。"
    ],
    "dayNumber": 1,
    "isCompleted": false
  },
  {
    "id": 2806,
    "title": "了解EB-5项目规则",
    "category": "风险管理",
    "subcategory": "防欺诈",
    "description": "了解EB-5规则可以减少受虚假陈述影响的可能性。投资者在投入资金前应了解投资、创造就业和维持要求。",
    "shortDescription": "了解EB-5规则可以减少受虚假陈述影响的可能性。",
    "examples": [
      "投资者了解到，根据EB-5法律，保证回报是不允许的。",
      "熟悉I-526表格的内容有助于投资者发现缺失的证据。"
    ],
    "dayNumber": 1,
    "isCompleted": false
  },
  {
    "id": 2901,
    "title": "了解退出策略基础",
    "category": "风险管理",
    "subcategory": "EB-5 项目退出策略",
    "description": "退出策略概述了 EB-5 投资者在完成移民要求后如何以及何时可以收回其资本。这是项目评估的关键部分。",
    "shortDescription": "退出策略概述了 EB-5 投资者在完成移民要求后如何以及何时可以收回其资本。",
    "examples": [
      "项目计划包括在第六年进行一次拟议的再融资。",
      "与创造就业期后的资产出售相关的退出策略有助于确保合规性。"
    ],
    "dayNumber": 1,
    "isCompleted": false
  },
  {
    "id": 2902,
    "title": "通过再融资退出",
    "category": "风险管理",
    "subcategory": "EB-5 项目退出策略",
    "description": "许多项目计划在稳定后通过再融资偿还 EB-5 投资者。这在房地产领域很常见，因为收入流支持新的融资来替代 EB-5 资本。",
    "shortDescription": "许多项目计划在稳定后通过再融资偿还 EB-5 投资者。",
    "examples": [
      "一个多户公寓大楼通过银行贷款再融资，允许 EB-5 投资者退出。",
      "再融资发生在入住率达到 90% 且净营业收入目标达成后。"
    ],
    "dayNumber": 1,
    "isCompleted": false
  },
  {
    "id": 2903,
    "title": "通过出售房产退出",
    "category": "风险管理",
    "subcategory": "EB-5 项目退出策略",
    "description": "一些 EB-5 项目计划在完工并创造就业后出售开发的资产。出售所得随后用于偿还投资者。",
    "shortDescription": "一些 EB-5 项目计划在完工并创造就业后出售开发的资产。",
    "examples": [
      "开发商以目标价格将酒店出售给一家私募股权公司，以偿还 EB-5 资金。",
      "一个工业仓库在租赁后出售给机构买家。"
    ],
    "dayNumber": 1,
    "isCompleted": false
  },
  {
    "id": 2904,
    "title": "通过收入分成退出",
    "category": "风险管理",
    "subcategory": "EB-5 项目退出策略",
    "description": "在极少数情况下，EB-5 投资通过收入分成的方式分期偿还。虽然不太常见，但当长期收入支持定期分配时，可以使用此方法。",
    "shortDescription": "在极少数情况下，EB-5 投资通过收入分成的方式分期偿还。",
    "examples": [
      "一个娱乐场所使用门票收入在 8 年内返还投资者资本。",
      "企业根据业绩提供季度报告和股息支付。"
    ],
    "dayNumber": 1,
    "isCompleted": false
  },
  {
    "id": 2905,
    "title": "退出时间的限制",
    "category": "风险管理",
    "subcategory": "EB-5 项目退出策略",
    "description": "EB-5 资金必须在整个维持期内保持投资和风险。在投资者提交 I-829 表格之前不允许提前退出。退出策略必须考虑到这一时间安排。",
    "shortDescription": "EB-5 资金必须在整个维持期内保持投资和风险。",
    "examples": [
      "投资者在两年有条件居留期结束后才能获得偿还。",
      "再融资计划只有在最后一个 I-829 提交窗口完成后才会进行。"
    ],
    "dayNumber": 1,
    "isCompleted": false
  },
  {
    "id": 2906,
    "title": "退出规划的透明度",
    "category": "风险管理",
    "subcategory": "EB-5 项目退出策略",
    "description": "退出策略必须在发行文件中明确披露。投资者应寻求有关时间安排、还款方式、意外情况和法律结构的透明度。",
    "shortDescription": "退出策略必须在发行文件中明确披露。",
    "examples": [
      "私募备忘录概述了再融资条款、时间表和潜在风险。",
      "投资者在投入资本前与法律顾问审查退出条款。"
    ],
    "dayNumber": 1,
    "isCompleted": false
  },
  {
    "id": 3002,
    "title": "发行文件的法律审查",
    "category": "风险管理",
    "subcategory": "法律和财务保障",
    "description": "投资者应请法律顾问审查私募备忘录（PPM）、认购协议和所有发行材料，以识别风险并确认EB-5合规性。",
    "shortDescription": "投资者应请法律顾问审查私募备忘录（PPM）、认购协议和所有发行材料，以...",
    "examples": [
      "移民律师在PPM的资本部署部分标记出不一致之处。",
      "证券律师确认协议中明确保护了投资者权利。"
    ],
    "dayNumber": 1,
    "isCompleted": false
  },
  {
    "id": 3003,
    "title": "第三方基金管理",
    "category": "风险管理",
    "subcategory": "法律和财务保障",
    "description": "独立的基金管理人确保适当的会计和资金使用追踪。他们提供透明度，并降低开发商或区域中心滥用资金的风险。",
    "shortDescription": "独立的基金管理人确保适当的会计和资金使用追踪。",
    "examples": [
      "第三方基金经理监控资本部署，并向投资者提供季度报告。",
      "投资者在批准资金释放前要求管理人提供核实。"
    ],
    "dayNumber": 1,
    "isCompleted": false
  },
  {
    "id": 3004,
    "title": "开发商股权承诺",
    "category": "风险管理",
    "subcategory": "法律和财务保障",
    "description": "开发商贡献大量股权的项目显示出与投资者利益的高度一致。这降低了风险，并提高了项目完成和资本保全的可能性。",
    "shortDescription": "开发商贡献大量股权的项目显示出与投资者利益的高度一致。",
    "examples": [
      "开发商在接受EB-5资本前，从自己的资金中出资项目成本的20%。",
      "高股权参与表明了承诺和财务稳定性。"
    ],
    "dayNumber": 1,
    "isCompleted": false
  },
  {
    "id": 3005,
    "title": "证券合规与披露",
    "category": "风险管理",
    "subcategory": "法律和财务保障",
    "description": "EB-5投资必须遵守美国证券法。披露必须明确解释风险、费用、利益冲突和资金使用。需要适当的注册或许可。",
    "shortDescription": "EB-5投资必须遵守美国证券法。",
    "examples": [
      "PPM包括了SEC的D条例所要求的披露。",
      "误导性或缺失的信息可能会使发行人承担责任，并危及投资者的身份。"
    ],
    "dayNumber": 1,
    "isCompleted": false
  },
  {
    "id": 3006,
    "title": "定期报告和透明度",
    "category": "风险管理",
    "subcategory": "法律和财务保障",
    "description": "持续的更新和披露有助于投资者监控进展和合规性。值得信赖的项目会定期分享建设里程碑、创造就业数据和财务更新。",
    "shortDescription": "持续的更新和披露有助于投资者监控进展和合规性。",
    "examples": [
      "投资者每月收到项目的更新，其中包含工作指标和时间表。",
      "透明的沟通可以提高信心，并有助于及早发现问题。"
    ],
    "dayNumber": 1,
    "isCompleted": false
  }
]